{
	"status": 0,
	"itemCount": 2247,
	"itemIndexMin": 0,
	"itemIndexMax": 29,
	"loadMore": "载入更多",
	"next": {
		"id_user": 5534,
		"type": "userFeed",
		"itemsLimit": 30,
		"itemsIndexMin": 30
	},
	"isSuccess": true,
	"feeds": [
		{
			"formdocid": 681284,
			"senderid": 3297,
			"appid": 4,
			"formtypeid": 4,
			"wfstateseq": 6,
			"changedate": "2016-04-15 16:08:07",
			"msubject": "从《太阳的后裔》看韩剧进化史：老三宝变新N宝 ",
			"message_body": "所谓看英剧的鄙视看美剧的，看美剧的鄙视看日剧的，看日剧的鄙视看韩剧的，看韩剧的鄙视看中国港剧，看港剧的鄙视中国台剧，看台剧的鄙视内地剧，内地剧鄙视泰国剧…… （咦，说好的泰国剧鄙视越南剧呢？） 不管怎",
			"last_save_date": "2016-04-15 16:08:07",
			"UserVarcharField1": "",
			"UserIntField4": 830,
			"UserIntField5": 50462,
			"UserVarcharField2": "据说，在剧迷圈中，存在着这样的鄙视链：",
			"UserVarcharField3": "网络大电影",
			"UserVarcharField4": "",
			"UserGeoField1": {
				"longitude": null,
				"latitude": null
			},
			"loc_locname": "",
			"loc_shopname": "",
			"geoloc_id": 61083,
			"geoloc_uuid": "1AFCF352-3A75-2EAE-0DA9-ED51F130C08B",
			"targetgroupid": [],
			"store": {
				"stores_id": 830,
				"stores_enterdate": "2015-07-29 15:58:44",
				"stores_title": null,
				"stores_name": "影讯衙门",
				"stores_tel": "",
				"stores_address": null,
				"stores_mark": "",
				"stores_logo_id": 50127,
				"stores_background_id": 0,
				"stores_engname": null,
				"worktime": null,
				"stores_url": "https://www.tsml.com.hk/statichtml/bjmovie01/estores/Home/store.html?stid=830",
				"stores_logo_url": "img.php?sn=202fb910d0950b684b5fb3cdd000c8a3",
				"stores_background_url": "img.php?sn=",
				"favouriteCheck": false
			},
			"likeCount": 1,
			"repostedCount": 0,
			"commentCount": 0,
			"favouriteCheck": false,
			"last_wfforumnote": [],
			"keywords": [
				{
					"keywordtagid": 39,
					"keywordcaption": "影视界"
				},
				{
					"keywordtagid": 109,
					"keywordcaption": "发行"
				}
			],
			"isLiked": false,
			"Ref_feed": [],
			"Ref_user": [],
			"sender_name": "孔利华",
			"sender_pic": "",
			"collections": [
				{
					"collect_id": 74477,
					"col_subject": "",
					"col_body": "",
					"to_ref_url": null,
					"creatoruserid": 3297,
					"enterdate": "2016-04-15 14:34:41",
					"wfemltableid": 134555,
					"wfemltablesn": "GHOR2-S01NY-8RLNI-9TVIF",
					"elems": [
						{
							"id": 111714,
							"collect_id": 74477,
							"sortorder": 0,
							"creatoruserid": 3297,
							"subject": "",
							"messagebody": "",
							"wfemltableid": 134555,
							"geoloc": null,
							"geoname": "",
							"enterdate": "2016-04-15 14:34:41",
							"deleted": 1,
							"elem_sn": "64F83-UOYRT-6Z2IV-5OCBB",
							"wffilename": "640.jpg",
							"wfextension": "image/jpeg",
							"wfsize": 10342,
							"fileSn": "GHOR2-S01NY-8RLNI-9TVIF",
							"picwidth": 500,
							"picheight": 274,
							"url": "https://www.tsml.com.hk/statichtml/bjmovie01/site/public/image.php?sn=GHOR2-S01NY-8RLNI-9TVIF"
						},
						{
							"id": 5555,
							"collect_id": 74477,
							"sortorder": 0,
							"creatoruserid": 3297,
							"subject": "",
							"messagebody": "",
							"wfemltableid": 134555,
							"geoloc": null,
							"geoname": "",
							"enterdate": "2016-04-15 14:34:41",
							"deleted": 1,
							"elem_sn": "64F83-UOYRT-6Z2IV-5OCBB",
							"wffilename": "640.jpg",
							"wfextension": "image/jpeg",
							"wfsize": 10342,
							"fileSn": "GHOR2-S01NY-8RLNI-9TVIF",
							"picwidth": 500,
							"picheight": 274,
							"url": "https://www.tsml.com.hk/statichtml/bjmovie01/site/public/image.php?sn=GHOR2-S01NY-8RLNI-9TVIF"
						}
					]
				}
			]
		},
		{
			"formdocid": 681283,
			"senderid": 11111111111111,
			"appid": 4,
			"formtypeid": 4,
			"wfstateseq": 6,
			"changedate": "2016-04-15 16:07:22",
			"msubject": "4k+3D+120帧，李安的新片放起来有多难？",
			"message_body": "曾经看过李安的《十年一觉电影梦》，6年赋闲在家，后来……两届奥斯卡最佳导演，两届金球最佳导演，两届柏林金熊， 两届威尼斯金狮， 两届英国电影学院奖最佳导演，一届奥斯卡最佳外语片……家庭煮妇的往事，可以",
			"last_save_date": "2016-04-15 16:07:22",
			"UserVarcharField1": "",
			"UserIntField4": 830,
			"UserIntField5": 50463,
			"UserVarcharField2": "曾经看过李安的《十年一觉电影梦》，6年赋闲在家，后来……两届奥斯卡最佳导演，两届",
			"UserVarcharField3": "影视工业网",
			"UserVarcharField4": "",
			"UserGeoField1": {
				"longitude": null,
				"latitude": null
			},
			"loc_locname": "",
			"loc_shopname": "",
			"geoloc_id": 61084,
			"geoloc_uuid": "079C289D-BF0D-D7D2-1FA1-C924C40026B7",
			"targetgroupid": [],
			"store": {
				"stores_id": 830,
				"stores_enterdate": "2015-07-29 15:58:44",
				"stores_title": null,
				"stores_name": "影讯衙门",
				"stores_tel": "",
				"stores_address": null,
				"stores_mark": "",
				"stores_logo_id": 50127,
				"stores_background_id": 0,
				"stores_engname": null,
				"worktime": null,
				"stores_url": "https://www.tsml.com.hk/statichtml/bjmovie01/estores/Home/store.html?stid=830",
				"stores_logo_url": "img.php?sn=202fb910d0950b684b5fb3cdd000c8a3",
				"stores_background_url": "img.php?sn=",
				"favouriteCheck": false
			},
			"likeCount": 0,
			"repostedCount": 0,
			"commentCount": 0,
			"favouriteCheck": false,
			"last_wfforumnote": [],
			"keywords": [
				{
					"keywordtagid": 39,
					"keywordcaption": "影视界"
				},
				{
					"keywordtagid": 109,
					"keywordcaption": "发行"
				}
			],
			"isLiked": false,
			"Ref_feed": [],
			"Ref_user": [],
			"sender_name": "孔利华",
			"sender_pic": "rtrtrt",
			"collections": [
				{
					"collect_id": 74479,
					"col_subject": "",
					"col_body": "",
					"to_ref_url": null,
					"creatoruserid": 3297,
					"enterdate": "2016-04-15 14:38:53",
					"wfemltableid": 134557,
					"wfemltablesn": "PON8U-Y8SCJ-30V99-6M8R3",
					"elems": [
						{
							"id": 111716,
							"collect_id": 74479,
							"sortorder": 0,
							"creatoruserid": 3297,
							"subject": "",
							"messagebody": "",
							"wfemltableid": 134557,
							"geoloc": null,
							"geoname": "",
							"enterdate": "2016-04-15 14:38:53",
							"deleted": 1,
							"elem_sn": "1EM72-VS0XH-AXCFT-6GNLG",
							"wffilename": "640.jpg",
							"wfextension": "image/jpeg",
							"wfsize": 23478,
							"fileSn": "PON8U-Y8SCJ-30V99-6M8R3",
							"picwidth": 636,
							"picheight": 424,
							"url": "https://www.tsml.com.hk/statichtml/bjmovie01/site/public/image.php?sn=PON8U-Y8SCJ-30V99-6M8R3"
						}
					]
				}
			]
		},
		{
			"formdocid": 681282,
			"senderid": 3297,
			"appid": 4,
			"formtypeid": 4,
			"wfstateseq": 6,
			"changedate": "2016-04-15 16:06:35",
			"msubject": "韩寒电影版《三重门》启动 ONE联手亭东影业进军影视业 ",
			"message_body": "另外，韩寒旗下作家张皓宸《我与世界，只差一个你》的同名电影由岩井俊二监制，将于明年暑假上映。而说到自己旗下作家时，韩寒特意在屏幕上打出畅销书排行榜，而郭敬明刚好是排在张皓宸之下。当大家看到该图片时，都",
			"last_save_date": "2016-04-15 16:06:35",
			"UserVarcharField1": "",
			"UserIntField4": 830,
			"UserIntField5": 50466,
			"UserVarcharField2": "4月13日韩寒公布电影项目新计划，包括将于明年上映的航空航天题材影片《天空制造》",
			"UserVarcharField3": " 电影日报",
			"UserVarcharField4": "",
			"UserGeoField1": {
				"longitude": null,
				"latitude": null
			},
			"loc_locname": "",
			"loc_shopname": "",
			"geoloc_id": 61087,
			"geoloc_uuid": "37A0CDB6-FE1D-70BD-50FC-29770108458C",
			"targetgroupid": [],
			"store": {
				"stores_id": 830,
				"stores_enterdate": "2015-07-29 15:58:44",
				"stores_title": null,
				"stores_name": "影讯衙门",
				"stores_tel": "",
				"stores_address": null,
				"stores_mark": "",
				"stores_logo_id": 50127,
				"stores_background_id": 0,
				"stores_engname": null,
				"worktime": null,
				"stores_url": "https://www.tsml.com.hk/statichtml/bjmovie01/estores/Home/store.html?stid=830",
				"stores_logo_url": "img.php?sn=202fb910d0950b684b5fb3cdd000c8a3",
				"stores_background_url": "img.php?sn=",
				"favouriteCheck": false
			},
			"likeCount": 0,
			"repostedCount": 0,
			"commentCount": 0,
			"favouriteCheck": false,
			"last_wfforumnote": [],
			"keywords": [
				{
					"keywordtagid": 39,
					"keywordcaption": "影视界"
				},
				{
					"keywordtagid": 109,
					"keywordcaption": "发行"
				}
			],
			"isLiked": false,
			"Ref_feed": [],
			"Ref_user": [],
			"sender_name": "孔利华",
			"sender_pic": "",
			"collections": [
				{
					"collect_id": 74482,
					"col_subject": "",
					"col_body": "",
					"to_ref_url": null,
					"creatoruserid": 3297,
					"enterdate": "2016-04-15 14:53:20",
					"wfemltableid": 134560,
					"wfemltablesn": "SGPDJ-2VUG1-M35RL-V8OWJ",
					"elems": [
						{
							"id": 111719,
							"collect_id": 74482,
							"sortorder": 0,
							"creatoruserid": 3297,
							"subject": "",
							"messagebody": "",
							"wfemltableid": 134560,
							"geoloc": null,
							"geoname": "",
							"enterdate": "2016-04-15 14:53:21",
							"deleted": 1,
							"elem_sn": "9GHN3-XRBX7-8V9CW-P7H7S",
							"wffilename": "640.jpg",
							"wfextension": "image/jpeg",
							"wfsize": 12392,
							"fileSn": "SGPDJ-2VUG1-M35RL-V8OWJ",
							"picwidth": 550,
							"picheight": 366,
							"url": "https://www.tsml.com.hk/statichtml/bjmovie01/site/public/image.php?sn=SGPDJ-2VUG1-M35RL-V8OWJ"
						}
					]
				}
			]
		},
		{
			"formdocid": 681281,
			"senderid": 3297,
			"appid": 4,
			"formtypeid": 4,
			"wfstateseq": 6,
			"changedate": "2016-04-15 16:06:24",
			"msubject": "男导演里头，也就他最懂女人心",
			"message_body": "在香港，最会拍女人的导演，不是许鞍华，也不是王家卫。而是关锦鹏。有人评价他——比女人更懂女人。是他导演的《阮玲玉》，把张曼玉从一个花瓶，变成柏林影后。也是他导演的《胭脂扣》，使梅艳芳获得了唯一一尊金像",
			"last_save_date": "2016-04-15 16:06:24",
			"UserVarcharField1": "",
			"UserIntField4": 830,
			"UserIntField5": 50468,
			"UserVarcharField2": "在香港，最会拍女人的导演，不是许鞍华，也不是王家卫。",
			"UserVarcharField3": "独立鱼电影",
			"UserVarcharField4": "",
			"UserGeoField1": {
				"longitude": null,
				"latitude": null
			},
			"loc_locname": "",
			"loc_shopname": "",
			"geoloc_id": 61089,
			"geoloc_uuid": "4FDE2A50-EFCA-AAD3-540E-F6035D4204CB",
			"targetgroupid": [],
			"store": {
				"stores_id": 830,
				"stores_enterdate": "2015-07-29 15:58:44",
				"stores_title": null,
				"stores_name": "影讯衙门",
				"stores_tel": "",
				"stores_address": null,
				"stores_mark": "",
				"stores_logo_id": 50127,
				"stores_background_id": 0,
				"stores_engname": null,
				"worktime": null,
				"stores_url": "https://www.tsml.com.hk/statichtml/bjmovie01/estores/Home/store.html?stid=830",
				"stores_logo_url": "img.php?sn=202fb910d0950b684b5fb3cdd000c8a3",
				"stores_background_url": "img.php?sn=",
				"favouriteCheck": false
			},
			"likeCount": 0,
			"repostedCount": 0,
			"commentCount": 0,
			"favouriteCheck": false,
			"last_wfforumnote": [],
			"keywords": [
				{
					"keywordtagid": 39,
					"keywordcaption": "影视界"
				},
				{
					"keywordtagid": 109,
					"keywordcaption": "发行"
				}
			],
			"isLiked": false,
			"Ref_feed": [],
			"Ref_user": [],
			"sender_name": "孔利华",
			"sender_pic": "",
			"collections": [
				{
					"collect_id": 74484,
					"col_subject": "",
					"col_body": "",
					"to_ref_url": null,
					"creatoruserid": 3297,
					"enterdate": "2016-04-15 14:58:08",
					"wfemltableid": 134562,
					"wfemltablesn": "ZF0L2-6V60Z-M6ECN-X4JZ4",
					"elems": [
						{
							"id": 111721,
							"collect_id": 74484,
							"sortorder": 0,
							"creatoruserid": 3297,
							"subject": "",
							"messagebody": "",
							"wfemltableid": 134562,
							"geoloc": null,
							"geoname": "",
							"enterdate": "2016-04-15 14:58:29",
							"deleted": 1,
							"elem_sn": "6CRNX-COD0C-JH6FP-EXIBJ",
							"wffilename": "Img277175019.jpg",
							"wfextension": "image/jpeg",
							"wfsize": 37782,
							"fileSn": "ZF0L2-6V60Z-M6ECN-X4JZ4",
							"picwidth": 300,
							"picheight": 364,
							"url": "https://www.tsml.com.hk/statichtml/bjmovie01/site/public/image.php?sn=ZF0L2-6V60Z-M6ECN-X4JZ4"
						}
					]
				}
			]
		},
		{
			"formdocid": 681280,
			"senderid": 3297,
			"appid": 4,
			"formtypeid": 4,
			"wfstateseq": 6,
			"changedate": "2016-04-15 16:05:50",
			"msubject": "很遗憾，看不到这部被禁的香港电影 ",
			"message_body": "我们都知道——时至今日的香港电影，早已不复当年。不得不承认。香港电影已经没落。鱼叔只能在老一辈香港导演中，看到昔日的感觉。杜琪峰就是其中之一。今年是他和韦家辉成立的电影公司——银河映像成立20周年。银",
			"last_save_date": "2016-04-15 16:05:50",
			"UserVarcharField1": "",
			"UserIntField4": 830,
			"UserIntField5": 50470,
			"UserVarcharField2": "我们都知道——时至今日的香港电影，早已不复当年。",
			"UserVarcharField3": "独立鱼电影",
			"UserVarcharField4": "",
			"UserGeoField1": {
				"longitude": null,
				"latitude": null
			},
			"loc_locname": "",
			"loc_shopname": "",
			"geoloc_id": 61091,
			"geoloc_uuid": "6259F732-DF8F-85C4-D43E-AF553190B667",
			"targetgroupid": [],
			"store": {
				"stores_id": 830,
				"stores_enterdate": "2015-07-29 15:58:44",
				"stores_title": null,
				"stores_name": "影讯衙门",
				"stores_tel": "",
				"stores_address": null,
				"stores_mark": "",
				"stores_logo_id": 50127,
				"stores_background_id": 0,
				"stores_engname": null,
				"worktime": null,
				"stores_url": "https://www.tsml.com.hk/statichtml/bjmovie01/estores/Home/store.html?stid=830",
				"stores_logo_url": "img.php?sn=202fb910d0950b684b5fb3cdd000c8a3",
				"stores_background_url": "img.php?sn=",
				"favouriteCheck": false
			},
			"likeCount": 0,
			"repostedCount": 0,
			"commentCount": 0,
			"favouriteCheck": false,
			"last_wfforumnote": [],
			"keywords": [
				{
					"keywordtagid": 39,
					"keywordcaption": "影视界"
				},
				{
					"keywordtagid": 109,
					"keywordcaption": "发行"
				}
			],
			"isLiked": false,
			"Ref_feed": [],
			"Ref_user": [],
			"sender_name": "孔利华",
			"sender_pic": "",
			"collections": [
				{
					"collect_id": 74486,
					"col_subject": "",
					"col_body": "",
					"to_ref_url": null,
					"creatoruserid": 3297,
					"enterdate": "2016-04-15 15:01:34",
					"wfemltableid": 134564,
					"wfemltablesn": "AKZ7Q-A2KGH-EXD16-60Y6P",
					"elems": [
						{
							"id": 111723,
							"collect_id": 74486,
							"sortorder": 0,
							"creatoruserid": 3297,
							"subject": "",
							"messagebody": "",
							"wfemltableid": 134564,
							"geoloc": null,
							"geoname": "",
							"enterdate": "2016-04-15 15:01:34",
							"deleted": 1,
							"elem_sn": "8FXUW-SIWVL-GACXD-2BWJD",
							"wffilename": "640.jpg",
							"wfextension": "image/jpeg",
							"wfsize": 22421,
							"fileSn": "AKZ7Q-A2KGH-EXD16-60Y6P",
							"picwidth": 400,
							"picheight": 400,
							"url": "https://www.tsml.com.hk/statichtml/bjmovie01/site/public/image.php?sn=AKZ7Q-A2KGH-EXD16-60Y6P"
						}
					]
				}
			]
		},
		{
			"formdocid": 681279,
			"senderid": 3297,
			"appid": 4,
			"formtypeid": 4,
			"wfstateseq": 6,
			"changedate": "2016-04-15 16:05:23",
			"msubject": "李宇春、柳传志同台，百位明星百亿计划，乐视“生态共享之夜”秀的是什么？ ",
			"message_body": "乐视“生态共享之夜”刚刚在国家网球中心钻石球场落幕。梅赛德斯-奔驰C级车作为首席生态合作伙伴共同“跨界化反，驾驭改变”，数百位明星、行业大佬、乐迷齐聚狂欢，让整个生态大Party璀璨夺目。活动开始仅1",
			"last_save_date": "2016-04-15 16:05:23",
			"UserVarcharField1": "",
			"UserIntField4": 830,
			"UserIntField5": 50472,
			"UserVarcharField2": "乐视“生态共享之夜”刚刚在国家网球中心钻石球场落幕。梅赛德斯-奔驰C级车作为首席",
			"UserVarcharField3": " 广电独家",
			"UserVarcharField4": "",
			"UserGeoField1": {
				"longitude": null,
				"latitude": null
			},
			"loc_locname": "",
			"loc_shopname": "",
			"geoloc_id": 61093,
			"geoloc_uuid": "B4EB5EFD-781E-8729-607E-71BDA1B2E846",
			"targetgroupid": [],
			"store": {
				"stores_id": 830,
				"stores_enterdate": "2015-07-29 15:58:44",
				"stores_title": null,
				"stores_name": "影讯衙门",
				"stores_tel": "",
				"stores_address": null,
				"stores_mark": "",
				"stores_logo_id": 50127,
				"stores_background_id": 0,
				"stores_engname": null,
				"worktime": null,
				"stores_url": "https://www.tsml.com.hk/statichtml/bjmovie01/estores/Home/store.html?stid=830",
				"stores_logo_url": "img.php?sn=202fb910d0950b684b5fb3cdd000c8a3",
				"stores_background_url": "img.php?sn=",
				"favouriteCheck": false
			},
			"likeCount": 0,
			"repostedCount": 0,
			"commentCount": 0,
			"favouriteCheck": false,
			"last_wfforumnote": [],
			"keywords": [
				{
					"keywordtagid": 39,
					"keywordcaption": "影视界"
				},
				{
					"keywordtagid": 109,
					"keywordcaption": "发行"
				}
			],
			"isLiked": false,
			"Ref_feed": [],
			"Ref_user": [],
			"sender_name": "孔利华",
			"sender_pic": "",
			"collections": [
				{
					"collect_id": 74487,
					"col_subject": "",
					"col_body": "",
					"to_ref_url": null,
					"creatoruserid": 3297,
					"enterdate": "2016-04-15 15:05:33",
					"wfemltableid": 134565,
					"wfemltablesn": "S6F6W-QL9AL-CYCBQ-MDDWG",
					"elems": [
						{
							"id": 111724,
							"collect_id": 74487,
							"sortorder": 0,
							"creatoruserid": 3297,
							"subject": "",
							"messagebody": "",
							"wfemltableid": 134565,
							"geoloc": null,
							"geoname": "",
							"enterdate": "2016-04-15 15:05:34",
							"deleted": 1,
							"elem_sn": "35GJB-KOYXX-2BGL2-VZIY7",
							"wffilename": "640HK4XSZ5O.jpg",
							"wfextension": "image/jpeg",
							"wfsize": 31968,
							"fileSn": "S6F6W-QL9AL-CYCBQ-MDDWG",
							"picwidth": 640,
							"picheight": 427,
							"url": "https://www.tsml.com.hk/statichtml/bjmovie01/site/public/image.php?sn=S6F6W-QL9AL-CYCBQ-MDDWG"
						}
					]
				}
			]
		},
		{
			"formdocid": 681278,
			"senderid": 3297,
			"appid": 4,
			"formtypeid": 4,
			"wfstateseq": 6,
			"changedate": "2016-04-15 16:01:22",
			"msubject": "网络大电影由来及2016发展前景 ",
			"message_body": "4月10日，虎嗅举办了关于网络视频内容的线下沙龙，爱奇艺影业投资项目部总经理窦黎黎作为嘉宾，分享了《如何利用平台优势孵化网络大电影》的演讲，以下为演讲记录。我们在2014年时，对网络大电影（以下简称“",
			"last_save_date": "2016-04-15 16:01:22",
			"UserVarcharField1": "",
			"UserIntField4": 830,
			"UserIntField5": 50473,
			"UserVarcharField2": "网络大电影由来及2016发展前景 ",
			"UserVarcharField3": "影视独舌",
			"UserVarcharField4": "",
			"UserGeoField1": {
				"longitude": null,
				"latitude": null
			},
			"loc_locname": "",
			"loc_shopname": "",
			"geoloc_id": 61094,
			"geoloc_uuid": "CB9A3885-B80F-70B2-9324-E8BD06DE60A0",
			"targetgroupid": [],
			"store": {
				"stores_id": 830,
				"stores_enterdate": "2015-07-29 15:58:44",
				"stores_title": null,
				"stores_name": "影讯衙门",
				"stores_tel": "",
				"stores_address": null,
				"stores_mark": "",
				"stores_logo_id": 50127,
				"stores_background_id": 0,
				"stores_engname": null,
				"worktime": null,
				"stores_url": "https://www.tsml.com.hk/statichtml/bjmovie01/estores/Home/store.html?stid=830",
				"stores_logo_url": "img.php?sn=202fb910d0950b684b5fb3cdd000c8a3",
				"stores_background_url": "img.php?sn=",
				"favouriteCheck": false
			},
			"likeCount": 0,
			"repostedCount": 0,
			"commentCount": 0,
			"favouriteCheck": false,
			"last_wfforumnote": [],
			"keywords": [
				{
					"keywordtagid": 39,
					"keywordcaption": "影视界"
				},
				{
					"keywordtagid": 109,
					"keywordcaption": "发行"
				}
			],
			"isLiked": false,
			"Ref_feed": [],
			"Ref_user": [],
			"sender_name": "孔利华",
			"sender_pic": "",
			"collections": [
				{
					"collect_id": 74489,
					"col_subject": "",
					"col_body": "",
					"to_ref_url": null,
					"creatoruserid": 3297,
					"enterdate": "2016-04-15 15:10:09",
					"wfemltableid": 134567,
					"wfemltablesn": "JAIEE-KO7LT-Q40ZS-FPF8G",
					"elems": [
						{
							"id": 111726,
							"collect_id": 74489,
							"sortorder": 0,
							"creatoruserid": 3297,
							"subject": "",
							"messagebody": "",
							"wfemltableid": 134567,
							"geoloc": null,
							"geoname": "",
							"enterdate": "2016-04-15 15:10:10",
							"deleted": 1,
							"elem_sn": "6EZE8-6LZF1-R9HUS-UFC09",
							"wffilename": "64029FYGKJP.jpg",
							"wfextension": "image/jpeg",
							"wfsize": 11398,
							"fileSn": "JAIEE-KO7LT-Q40ZS-FPF8G",
							"picwidth": 640,
							"picheight": 269,
							"url": "https://www.tsml.com.hk/statichtml/bjmovie01/site/public/image.php?sn=JAIEE-KO7LT-Q40ZS-FPF8G"
						}
					]
				}
			]
		},
		{
			"formdocid": 681277,
			"senderid": 3297,
			"appid": 4,
			"formtypeid": 4,
			"wfstateseq": 6,
			"changedate": "2016-04-15 15:59:57",
			"msubject": "中国文化产业蓝皮书：新兴文化消费用户付费意愿增强",
			"message_body": "近日，中国社会科学院文化研究中心组织编写的《文化蓝皮书：中国文化产业发展报告（2015~2016）》由社会科学文献出版社出版发行。蓝皮书指出，传统文化消费和新兴文化消费融合发展是现阶段文化消费的又一个",
			"last_save_date": "2016-04-15 15:59:57",
			"UserVarcharField1": "",
			"UserIntField4": 830,
			"UserIntField5": 50477,
			"UserVarcharField2": "近日，中国社会科学院文化研究中心组织编写的《文化蓝皮书：中国文化产业发展报告（2",
			"UserVarcharField3": "中国影视版权观察",
			"UserVarcharField4": "",
			"UserGeoField1": {
				"longitude": null,
				"latitude": null
			},
			"loc_locname": "",
			"loc_shopname": "",
			"geoloc_id": 61098,
			"geoloc_uuid": "5E49E43B-BA37-5486-9112-60E9C403B1FE",
			"targetgroupid": [],
			"store": {
				"stores_id": 830,
				"stores_enterdate": "2015-07-29 15:58:44",
				"stores_title": null,
				"stores_name": "影讯衙门",
				"stores_tel": "",
				"stores_address": null,
				"stores_mark": "",
				"stores_logo_id": 50127,
				"stores_background_id": 0,
				"stores_engname": null,
				"worktime": null,
				"stores_url": "https://www.tsml.com.hk/statichtml/bjmovie01/estores/Home/store.html?stid=830",
				"stores_logo_url": "img.php?sn=202fb910d0950b684b5fb3cdd000c8a3",
				"stores_background_url": "img.php?sn=",
				"favouriteCheck": false
			},
			"likeCount": 0,
			"repostedCount": 0,
			"commentCount": 0,
			"favouriteCheck": false,
			"last_wfforumnote": [],
			"keywords": [
				{
					"keywordtagid": 39,
					"keywordcaption": "影视界"
				},
				{
					"keywordtagid": 109,
					"keywordcaption": "发行"
				}
			],
			"isLiked": false,
			"Ref_feed": [],
			"Ref_user": [],
			"sender_name": "孔利华",
			"sender_pic": "",
			"collections": [
				{
					"collect_id": 74493,
					"col_subject": "",
					"col_body": "",
					"to_ref_url": null,
					"creatoruserid": 3297,
					"enterdate": "2016-04-15 15:22:27",
					"wfemltableid": 134572,
					"wfemltablesn": "J4C4A-2TBI3-X53MI-RCDGP",
					"elems": [
						{
							"id": 111731,
							"collect_id": 74493,
							"sortorder": 0,
							"creatoruserid": 3297,
							"subject": "",
							"messagebody": "",
							"wfemltableid": 134572,
							"geoloc": null,
							"geoname": "",
							"enterdate": "2016-04-15 15:23:52",
							"deleted": 1,
							"elem_sn": "7K7XS-P5VNI-RMCSN-6UD5J",
							"wffilename": "middle_20091219_80c0c623e91df9dd6acay60XOE5eZy2o.jpg",
							"wfextension": "image/jpeg",
							"wfsize": 42013,
							"fileSn": "J4C4A-2TBI3-X53MI-RCDGP",
							"picwidth": 780,
							"picheight": 728,
							"url": "https://www.tsml.com.hk/statichtml/bjmovie01/site/public/image.php?sn=J4C4A-2TBI3-X53MI-RCDGP"
						}
					]
				}
			]
		},
		{
			"formdocid": 681276,
			"senderid": 3297,
			"appid": 4,
			"formtypeid": 4,
			"wfstateseq": 6,
			"changedate": "2016-04-15 15:59:39",
			"msubject": "2016年的古装剧谁能扛鼎？ ",
			"message_body": "近年来国产剧达到“爆款”级别的几乎都是古装剧，如《甄嬛传》、《琅琊榜》、《古剑奇谭》、《花千骨》等，为了实现2016年收视率的开门红，一、二线卫视纷纷把宝押在了古装剧上。而今年春节档，更是首次出现古装",
			"last_save_date": "2016-04-15 15:59:39",
			"UserVarcharField1": "",
			"UserIntField4": 830,
			"UserIntField5": 50481,
			"UserVarcharField2": "近年来国产剧达到“爆款”级别的几乎都是古装剧，如《甄嬛传》、《琅琊榜》、《古剑奇",
			"UserVarcharField3": "中国影视版权观察",
			"UserVarcharField4": "",
			"UserGeoField1": {
				"longitude": null,
				"latitude": null
			},
			"loc_locname": "",
			"loc_shopname": "",
			"geoloc_id": 61102,
			"geoloc_uuid": "E3DE8C49-FFED-3CE3-EB96-E8CBC1AEC872",
			"targetgroupid": [],
			"store": {
				"stores_id": 830,
				"stores_enterdate": "2015-07-29 15:58:44",
				"stores_title": null,
				"stores_name": "影讯衙门",
				"stores_tel": "",
				"stores_address": null,
				"stores_mark": "",
				"stores_logo_id": 50127,
				"stores_background_id": 0,
				"stores_engname": null,
				"worktime": null,
				"stores_url": "https://www.tsml.com.hk/statichtml/bjmovie01/estores/Home/store.html?stid=830",
				"stores_logo_url": "img.php?sn=202fb910d0950b684b5fb3cdd000c8a3",
				"stores_background_url": "img.php?sn=",
				"favouriteCheck": false
			},
			"likeCount": 0,
			"repostedCount": 0,
			"commentCount": 0,
			"favouriteCheck": false,
			"last_wfforumnote": [],
			"keywords": [
				{
					"keywordtagid": 39,
					"keywordcaption": "影视界"
				},
				{
					"keywordtagid": 109,
					"keywordcaption": "发行"
				}
			],
			"isLiked": false,
			"Ref_feed": [],
			"Ref_user": [],
			"sender_name": "孔利华",
			"sender_pic": "",
			"collections": [
				{
					"collect_id": 74496,
					"col_subject": "",
					"col_body": "",
					"to_ref_url": null,
					"creatoruserid": 3297,
					"enterdate": "2016-04-15 15:36:55",
					"wfemltableid": 134574,
					"wfemltablesn": "F2KUV-6WENJ-3N2S6-2B6VR",
					"elems": [
						{
							"id": 111733,
							"collect_id": 74496,
							"sortorder": 0,
							"creatoruserid": 3297,
							"subject": "",
							"messagebody": "",
							"wfemltableid": 134574,
							"geoloc": null,
							"geoname": "",
							"enterdate": "2016-04-15 15:36:57",
							"deleted": 1,
							"elem_sn": "9L5KD-SMWUK-8AM69-HALSJ",
							"wffilename": "6402M1312KX.jpg",
							"wfextension": "image/jpeg",
							"wfsize": 55662,
							"fileSn": "F2KUV-6WENJ-3N2S6-2B6VR",
							"picwidth": 481,
							"picheight": 800,
							"url": "https://www.tsml.com.hk/statichtml/bjmovie01/site/public/image.php?sn=F2KUV-6WENJ-3N2S6-2B6VR"
						}
					]
				}
			]
		},
		{
			"formdocid": 681275,
			"senderid": 3297,
			"appid": 4,
			"formtypeid": 4,
			"wfstateseq": 6,
			"changedate": "2016-04-15 15:59:22",
			"msubject": "电影开场镜头的十种典型手法 ",
			"message_body": "电影若只如初见，对于任何电影来说，开场镜头就好像打开光影世界大门的钥匙，引领观众开启电影之旅。可以说，一部电影能否在一瞬间抓住观众的眼球，和观众产生良好的化学反应，开场镜头扮演着重要的角色，因而对于导",
			"last_save_date": "2016-04-15 15:59:22",
			"UserVarcharField1": "",
			"UserIntField4": 830,
			"UserIntField5": 50483,
			"UserVarcharField2": "电影若只如初见，对于任何电影来说，开场镜头就好像打开光影世界大门的钥匙，引领观众",
			"UserVarcharField3": " 追梦编剧人",
			"UserVarcharField4": "",
			"UserGeoField1": {
				"longitude": null,
				"latitude": null
			},
			"loc_locname": "",
			"loc_shopname": "",
			"geoloc_id": 61104,
			"geoloc_uuid": "4F74EB56-35DF-D399-6F84-C128AC546001",
			"targetgroupid": [],
			"store": {
				"stores_id": 830,
				"stores_enterdate": "2015-07-29 15:58:44",
				"stores_title": null,
				"stores_name": "影讯衙门",
				"stores_tel": "",
				"stores_address": null,
				"stores_mark": "",
				"stores_logo_id": 50127,
				"stores_background_id": 0,
				"stores_engname": null,
				"worktime": null,
				"stores_url": "https://www.tsml.com.hk/statichtml/bjmovie01/estores/Home/store.html?stid=830",
				"stores_logo_url": "img.php?sn=202fb910d0950b684b5fb3cdd000c8a3",
				"stores_background_url": "img.php?sn=",
				"favouriteCheck": false
			},
			"likeCount": 0,
			"repostedCount": 0,
			"commentCount": 0,
			"favouriteCheck": false,
			"last_wfforumnote": [],
			"keywords": [
				{
					"keywordtagid": 39,
					"keywordcaption": "影视界"
				},
				{
					"keywordtagid": 109,
					"keywordcaption": "发行"
				}
			],
			"isLiked": false,
			"Ref_feed": [],
			"Ref_user": [],
			"sender_name": "孔利华",
			"sender_pic": "",
			"collections": [
				{
					"collect_id": 74499,
					"col_subject": "",
					"col_body": "",
					"to_ref_url": null,
					"creatoruserid": 3297,
					"enterdate": "2016-04-15 15:40:41",
					"wfemltableid": 134577,
					"wfemltablesn": "XMHOX-HXZZX-5TE5A-SCZJE",
					"elems": [
						{
							"id": 111736,
							"collect_id": 74499,
							"sortorder": 0,
							"creatoruserid": 3297,
							"subject": "",
							"messagebody": "",
							"wfemltableid": 134577,
							"geoloc": null,
							"geoname": "",
							"enterdate": "2016-04-15 15:40:46",
							"deleted": 1,
							"elem_sn": "77ZMW-7R031-NQDRH-SWU22",
							"wffilename": "640Z45012W1.jpg",
							"wfextension": "image/jpeg",
							"wfsize": 20702,
							"fileSn": "XMHOX-HXZZX-5TE5A-SCZJE",
							"picwidth": 640,
							"picheight": 445,
							"url": "https://www.tsml.com.hk/statichtml/bjmovie01/site/public/image.php?sn=XMHOX-HXZZX-5TE5A-SCZJE"
						}
					]
				}
			]
		},
		{
			"formdocid": 664581,
			"senderid": 7345,
			"appid": 5,
			"formtypeid": 5,
			"wfstateseq": 6,
			"changedate": "2016-04-15 11:50:51",
			"msubject": "",
			"message_body": "",
			"last_save_date": "2016-04-15 11:50:51",
			"UserVarcharField1": "",
			"UserIntField4": 653902,
			"UserIntField5": 653902,
			"UserVarcharField2": "",
			"UserVarcharField3": "",
			"UserVarcharField4": "",
			"UserGeoField1": {
				"longitude": null,
				"latitude": null
			},
			"loc_locname": "",
			"loc_shopname": "",
			"geoloc_id": "",
			"geoloc_uuid": "",
			"targetgroupid": [],
			"likeCount": 0,
			"repostedCount": 0,
			"commentCount": 0,
			"favouriteCheck": false,
			"last_wfforumnote": [],
			"keywords": [],
			"isLiked": false,
			"Ref_feed": {
				"formdocid": 653902,
				"senderid": 9946,
				"appid": 4,
				"formtypeid": 4,
				"wfstateseq": 6,
				"changedate": "2016-04-15 10:48:37",
				"msubject": "为证没整容 47岁的伊能静也用了揉脸这招",
				"message_body": "　　导语：“整容传闻”总是女星们的大忌，为了证明自己是“纯天然”美人，这些明星都没少付诸行动。这不，前几天伊能静在自己的微博中PO了一段自拍小视频，不断推眉毛、揉脸颊，解释自己之所以脸不对称，是因为“",
				"last_save_date": "2016-04-15 10:48:37",
				"UserVarcharField1": "",
				"UserIntField4": 1188,
				"UserIntField5": 50443,
				"UserVarcharField2": "　导语：“整容传闻”总是女星们的大忌，为了证明自己是“纯天然”美人，这些明星都没",
				"UserVarcharField3": "佚名",
				"UserVarcharField4": null,
				"loc_locname": null,
				"loc_shopname": null,
				"geoloc_id": 61061,
				"geoloc_uuid": "FA0B0B2D-945C-E0D1-3F29-42FD39199500",
				"store": {
					"stores_id": 1188,
					"stores_enterdate": "2015-09-23 11:22:35",
					"stores_title": null,
					"stores_name": "和沐新闻",
					"stores_tel": "",
					"stores_address": null,
					"stores_mark": "",
					"stores_logo_id": 122317,
					"stores_background_id": 0,
					"stores_engname": null,
					"worktime": null,
					"stores_url": "https://www.tsml.com.hk/statichtml/bjmovie01/estores/Home/store.html?stid=1188",
					"stores_logo_url": "img.php?sn=5RHZ1-7ZKT7-6P52A-Q7BHT",
					"stores_background_url": "img.php?sn=",
					"favouriteCheck": false
				},
				"collections": [
					{
						"collect_id": 74460,
						"col_subject": "",
						"col_body": "",
						"to_ref_url": null,
						"creatoruserid": 9946,
						"enterdate": "2016-04-15 10:48:12",
						"wfemltableid": 134512,
						"wfemltablesn": "VFBE3-DHGCS-ETAJW-HW0TB",
						"elems": [
							{
								"id": 111673,
								"collect_id": 74460,
								"sortorder": 0,
								"creatoruserid": 9946,
								"subject": "",
								"messagebody": "",
								"wfemltableid": 134512,
								"geoloc": null,
								"geoname": "",
								"enterdate": "2016-04-15 10:48:13",
								"deleted": 1,
								"elem_sn": "2TO8L-R45PT-1TUAM-NL36U",
								"wffilename": "22.jpg",
								"wfextension": "image/jpeg",
								"wfsize": 123860,
								"fileSn": "VFBE3-DHGCS-ETAJW-HW0TB",
								"picwidth": 479,
								"picheight": 479,
								"url": "https://www.tsml.com.hk/statichtml/bjmovie01/site/public/image.php?sn=VFBE3-DHGCS-ETAJW-HW0TB"
							}
						]
					}
				],
				"sender_name": "薄冰",
				"sender_pic": "https://www.tsml.com.hk/statichtml/bjmovie01/site/public/image.php?sn=FSUF3-DFOAA-ND82L-D5NSV"
			},
			"Ref_user": {
				"viewUserName": "薄冰",
				"profile_pic": "https://www.tsml.com.hk/statichtml/bjmovie01/site/public/image.php?sn=FSUF3-DFOAA-ND82L-D5NSV"
			},
			"sender_name": "Ahb gmail sh android",
			"sender_pic": "https://www.tsml.com.hk/statichtml/bjmovie01/site/public/image.php?sn=O1G3P-8MOZA-QU23H-EN0A6",
			"collections": []
		},
		{
			"formdocid": 653892,
			"senderid": 7311,
			"appid": 5,
			"formtypeid": 5,
			"wfstateseq": 6,
			"changedate": "2016-04-15 09:52:11",
			"msubject": "哼哼哈嘿。。。",
			"message_body": "",
			"last_save_date": "2016-04-15 09:52:11",
			"UserVarcharField1": "",
			"UserIntField4": "",
			"UserIntField5": "",
			"UserVarcharField2": "",
			"UserVarcharField3": "",
			"UserVarcharField4": "",
			"UserGeoField1": {
				"longitude": null,
				"latitude": null
			},
			"loc_locname": "",
			"loc_shopname": "",
			"geoloc_id": "",
			"geoloc_uuid": "",
			"targetgroupid": [],
			"likeCount": 0,
			"repostedCount": 0,
			"commentCount": 0,
			"favouriteCheck": false,
			"last_wfforumnote": [],
			"keywords": [],
			"isLiked": false,
			"Ref_feed": [],
			"Ref_user": [],
			"sender_name": "祁 心胜",
			"sender_pic": "https://www.tsml.com.hk/statichtml/bjmovie01/site/public/image.php?sn=CABV1-WLPHM-45Z8J-0WCP9",
			"collections": [
				{
					"collect_id": 74446,
					"col_subject": "",
					"col_body": "",
					"to_ref_url": null,
					"creatoruserid": 7311,
					"enterdate": "2016-04-15 09:52:06",
					"wfemltableid": 0,
					"wfemltablesn": "",
					"elems": [
						{
							"id": 111664,
							"collect_id": 74446,
							"sortorder": 0,
							"creatoruserid": 7311,
							"subject": "",
							"messagebody": "",
							"wfemltableid": 134503,
							"geoloc": null,
							"geoname": "",
							"enterdate": "2016-04-15 10:19:15",
							"deleted": 1,
							"elem_sn": "9ZSOH-5AXUK-AT7D8-TOOHD",
							"wffilename": "11.jpg",
							"wfextension": "image/jpeg",
							"wfsize": 300118,
							"fileSn": "H4RUY-6QZC1-JPET4-TLH8N",
							"picwidth": 1080,
							"picheight": 1920,
							"url": "https://www.tsml.com.hk/statichtml/bjmovie01/site/public/image.php?sn=H4RUY-6QZC1-JPET4-TLH8N"
						},
						{
							"id": 111653,
							"collect_id": 74446,
							"sortorder": 0,
							"creatoruserid": 7311,
							"subject": "",
							"messagebody": "",
							"wfemltableid": 134492,
							"geoloc": null,
							"geoname": "",
							"enterdate": "2016-04-15 09:52:06",
							"deleted": 1,
							"elem_sn": "4UW1O-A2GSU-X32TT-2T6OK",
							"wffilename": "1460684993823.mp4",
							"wfextension": "video/mp4",
							"wfsize": 663147,
							"fileSn": "KI1KF-VP8BZ-UUR3I-HJNM8",
							"picwidth": 480,
							"picheight": 480,
							"url": "https://www.tsml.com.hk/statichtml/bjmovie01/site/public/viewVideoThumb.php?sn=KI1KF-VP8BZ-UUR3I-HJNM8",
							"videourl": "https://www.tsml.com.hk/statichtml/bjmovie01/site/public/viewVideo.php?sn=KI1KF-VP8BZ-UUR3I-HJNM8"
						}
					]
				}
			]
		},
		{
			"formdocid": 642687,
			"senderid": 3297,
			"appid": 4,
			"formtypeid": 4,
			"wfstateseq": 6,
			"changedate": "2016-04-14 16:23:55",
			"msubject": "2016编剧新生态全解析",
			"message_body": "编剧行业自身正在经历嬗变。资本为何青睐编剧？有组织的编剧们，究竟有多大话语权？编剧中心制是否可行？新媒体的崛起又为编剧行业增加了哪些变数，是否出现新的生产、分配方式？  3月22日，演员王宝强首次自导",
			"last_save_date": "2016-04-14 16:23:55",
			"UserVarcharField1": "",
			"UserIntField4": 830,
			"UserIntField5": 50359,
			"UserVarcharField2": "编剧行业自身正在经历嬗变。资本为何青睐编剧？有组织的编剧们，究竟有多大话语权？编",
			"UserVarcharField3": "编剧帮",
			"UserVarcharField4": "",
			"UserGeoField1": {
				"longitude": null,
				"latitude": null
			},
			"loc_locname": "",
			"loc_shopname": "",
			"geoloc_id": 60948,
			"geoloc_uuid": "1644C397-E62D-AB6D-6BC4-A3C4314B9992",
			"targetgroupid": [],
			"store": {
				"stores_id": 830,
				"stores_enterdate": "2015-07-29 15:58:44",
				"stores_title": null,
				"stores_name": "影讯衙门",
				"stores_tel": "",
				"stores_address": null,
				"stores_mark": "",
				"stores_logo_id": 50127,
				"stores_background_id": 0,
				"stores_engname": null,
				"worktime": null,
				"stores_url": "https://www.tsml.com.hk/statichtml/bjmovie01/estores/Home/store.html?stid=830",
				"stores_logo_url": "img.php?sn=202fb910d0950b684b5fb3cdd000c8a3",
				"stores_background_url": "img.php?sn=",
				"favouriteCheck": false
			},
			"likeCount": 1,
			"repostedCount": 0,
			"commentCount": 2,
			"favouriteCheck": false,
			"last_wfforumnote": {
				"c_forumnoteid": 0,
				"formdocid": 642687,
				"forumnoteid": 92254,
				"forumnotetypeid": 0,
				"enterdate": "2016-04-14 18:44:34",
				"crmk": "See",
				"geoloc_id": null,
				"userid": 537,
				"wfemltableid": null,
				"share_docid": null,
				"actiontype": null,
				"user": {
					"id_user": 537,
					"username": "And william",
					"surname": null,
					"firstname": null,
					"publishedname": "And william",
					"gender": "M",
					"selfdesc": "php manager, app",
					"statusmessage": "iOS the best",
					"picwfemltableid": 123321,
					"bkgdwfemltableid": 121843,
					"personalemail": "ahbone@hotmail.com",
					"viewUserName": "And william"
				}
			},
			"keywords": [
				{
					"keywordtagid": 39,
					"keywordcaption": "影视界"
				},
				{
					"keywordtagid": 109,
					"keywordcaption": "发行"
				}
			],
			"isLiked": false,
			"Ref_feed": [],
			"Ref_user": [],
			"sender_name": "孔利华",
			"sender_pic": "",
			"collections": [
				{
					"collect_id": 74370,
					"col_subject": "",
					"col_body": "",
					"to_ref_url": null,
					"creatoruserid": 3297,
					"enterdate": "2016-04-14 16:13:34",
					"wfemltableid": 134416,
					"wfemltablesn": "Z5OEB-VFA48-XTPUZ-WE75S",
					"elems": [
						{
							"id": 111587,
							"collect_id": 74370,
							"sortorder": 0,
							"creatoruserid": 3297,
							"subject": "",
							"messagebody": "",
							"wfemltableid": 134416,
							"geoloc": null,
							"geoname": "",
							"enterdate": "2016-04-14 16:20:48",
							"deleted": 1,
							"elem_sn": "21XIL-PBVPK-6AED2-Z76G9",
							"wffilename": "640.jpg",
							"wfextension": "image/jpeg",
							"wfsize": 22635,
							"fileSn": "Z5OEB-VFA48-XTPUZ-WE75S",
							"picwidth": 640,
							"picheight": 427,
							"url": "https://www.tsml.com.hk/statichtml/bjmovie01/site/public/image.php?sn=Z5OEB-VFA48-XTPUZ-WE75S"
						}
					]
				}
			]
		},
		{
			"formdocid": 642686,
			"senderid": 3297,
			"appid": 4,
			"formtypeid": 4,
			"wfstateseq": 6,
			"changedate": "2016-04-14 16:23:51",
			"msubject": "五一小长假，如何愉快地玩转北京周边长城？ ",
			"message_body": "中国万里长城是世界上修建时间最长，工程量最大的冷兵器战争时代的国家军事性防御工程，凝聚着我们祖先的血汗和智慧，是中华民族的象征和骄傲。长城全长大约6700 公里，通称“万里长城”。长城的修建持续了两千",
			"last_save_date": "2016-04-14 16:23:51",
			"UserVarcharField1": "",
			"UserIntField4": 830,
			"UserIntField5": 50357,
			"UserVarcharField2": "中国万里长城是世界上修建时间最长，工程量最大的冷兵器战争时代的国家军事性防御工程",
			"UserVarcharField3": "和沐传媒",
			"UserVarcharField4": "",
			"UserGeoField1": {
				"longitude": null,
				"latitude": null
			},
			"loc_locname": "",
			"loc_shopname": "",
			"geoloc_id": 60946,
			"geoloc_uuid": "6D2A0552-7F9D-273C-F361-311FB86605D0",
			"targetgroupid": [],
			"store": {
				"stores_id": 830,
				"stores_enterdate": "2015-07-29 15:58:44",
				"stores_title": null,
				"stores_name": "影讯衙门",
				"stores_tel": "",
				"stores_address": null,
				"stores_mark": "",
				"stores_logo_id": 50127,
				"stores_background_id": 0,
				"stores_engname": null,
				"worktime": null,
				"stores_url": "https://www.tsml.com.hk/statichtml/bjmovie01/estores/Home/store.html?stid=830",
				"stores_logo_url": "img.php?sn=202fb910d0950b684b5fb3cdd000c8a3",
				"stores_background_url": "img.php?sn=",
				"favouriteCheck": false
			},
			"likeCount": 0,
			"repostedCount": 0,
			"commentCount": 0,
			"favouriteCheck": false,
			"last_wfforumnote": [],
			"keywords": [
				{
					"keywordtagid": 39,
					"keywordcaption": "影视界"
				},
				{
					"keywordtagid": 118,
					"keywordcaption": "场地"
				}
			],
			"isLiked": false,
			"Ref_feed": [],
			"Ref_user": [],
			"sender_name": "孔利华",
			"sender_pic": "",
			"collections": [
				{
					"collect_id": 74369,
					"col_subject": "",
					"col_body": "",
					"to_ref_url": null,
					"creatoruserid": 3297,
					"enterdate": "2016-04-14 16:10:40",
					"wfemltableid": 134413,
					"wfemltablesn": "AA6PX-SJXFB-B8N3U-M2D8V",
					"elems": [
						{
							"id": 111584,
							"collect_id": 74369,
							"sortorder": 0,
							"creatoruserid": 3297,
							"subject": "",
							"messagebody": "",
							"wfemltableid": 134413,
							"geoloc": null,
							"geoname": "",
							"enterdate": "2016-04-14 16:10:41",
							"deleted": 1,
							"elem_sn": "4LXT5-N8U5K-LYLJ0-6HTQI",
							"wffilename": "640.jpg",
							"wfextension": "image/jpeg",
							"wfsize": 34048,
							"fileSn": "AA6PX-SJXFB-B8N3U-M2D8V",
							"picwidth": 640,
							"picheight": 227,
							"url": "https://www.tsml.com.hk/statichtml/bjmovie01/site/public/image.php?sn=AA6PX-SJXFB-B8N3U-M2D8V"
						}
					]
				}
			]
		},
		{
			"formdocid": 642685,
			"senderid": 3297,
			"appid": 4,
			"formtypeid": 4,
			"wfstateseq": 6,
			"changedate": "2016-04-14 16:23:47",
			"msubject": "尹鸿《网络剧的底线可以比电视剧低吗》",
			"message_body": "吴宇森说：拍电影就是不断解决困难的过程。但是在国内的大部分剧组，这些本该避免的困难，频繁发生，我们时常听到某某剧组因为丢失素材、伙食太差、导演和制片人有矛盾而停工。对于很多新生导演来说，每一部影片的开",
			"last_save_date": "2016-04-14 16:23:47",
			"UserVarcharField1": "",
			"UserIntField4": 830,
			"UserIntField5": 50355,
			"UserVarcharField2": "吴宇森说：拍电影就是不断解决困难的过程。但是在国内的大部分剧组，这些本该避免的困",
			"UserVarcharField3": "影视新生代",
			"UserVarcharField4": "",
			"UserGeoField1": {
				"longitude": null,
				"latitude": null
			},
			"loc_locname": "",
			"loc_shopname": "",
			"geoloc_id": 60944,
			"geoloc_uuid": "B6F3CFF9-1A59-A1E0-4D5B-C92BB1DC9A2C",
			"targetgroupid": [],
			"store": {
				"stores_id": 830,
				"stores_enterdate": "2015-07-29 15:58:44",
				"stores_title": null,
				"stores_name": "影讯衙门",
				"stores_tel": "",
				"stores_address": null,
				"stores_mark": "",
				"stores_logo_id": 50127,
				"stores_background_id": 0,
				"stores_engname": null,
				"worktime": null,
				"stores_url": "https://www.tsml.com.hk/statichtml/bjmovie01/estores/Home/store.html?stid=830",
				"stores_logo_url": "img.php?sn=202fb910d0950b684b5fb3cdd000c8a3",
				"stores_background_url": "img.php?sn=",
				"favouriteCheck": false
			},
			"likeCount": 0,
			"repostedCount": 0,
			"commentCount": 0,
			"favouriteCheck": false,
			"last_wfforumnote": [],
			"keywords": [
				{
					"keywordtagid": 39,
					"keywordcaption": "影视界"
				},
				{
					"keywordtagid": 109,
					"keywordcaption": "发行"
				}
			],
			"isLiked": false,
			"Ref_feed": [],
			"Ref_user": [],
			"sender_name": "孔利华",
			"sender_pic": "",
			"collections": [
				{
					"collect_id": 74368,
					"col_subject": "",
					"col_body": "",
					"to_ref_url": null,
					"creatoruserid": 3297,
					"enterdate": "2016-04-14 16:09:10",
					"wfemltableid": 134412,
					"wfemltablesn": "OJBX9-XFZKH-G6W6O-3O0RL",
					"elems": [
						{
							"id": 111583,
							"collect_id": 74368,
							"sortorder": 0,
							"creatoruserid": 3297,
							"subject": "",
							"messagebody": "",
							"wfemltableid": 134412,
							"geoloc": null,
							"geoname": "",
							"enterdate": "2016-04-14 16:09:11",
							"deleted": 1,
							"elem_sn": "50EJ9-C6UD6-0J9FT-APWHC",
							"wffilename": "640.jpg",
							"wfextension": "image/jpeg",
							"wfsize": 21508,
							"fileSn": "OJBX9-XFZKH-G6W6O-3O0RL",
							"picwidth": 583,
							"picheight": 369,
							"url": "https://www.tsml.com.hk/statichtml/bjmovie01/site/public/image.php?sn=OJBX9-XFZKH-G6W6O-3O0RL"
						}
					]
				}
			]
		},
		{
			"formdocid": 642684,
			"senderid": 3297,
			"appid": 4,
			"formtypeid": 4,
			"wfstateseq": 6,
			"changedate": "2016-04-14 16:23:44",
			"msubject": "网络剧与电视剧的规范方式是否应该尝试“求同存异”？ ",
			"message_body": "全国电视剧行业年会上，国家新闻出版广电总局网络视听节目管理司罗建辉司长在“网络剧的发展与管理”的主题报告中，着重强调了网络剧审查和监管的问题。“线上线下标准统一，电视不能播什么，网络也不行”的规定，随",
			"last_save_date": "2016-04-14 16:23:44",
			"UserVarcharField1": "",
			"UserIntField4": 830,
			"UserIntField5": 50352,
			"UserVarcharField2": "全国电视剧行业年会上，国家新闻出版广电总局网络视听节目管理司罗建辉司长在“网络剧",
			"UserVarcharField3": "编剧帮",
			"UserVarcharField4": "",
			"UserGeoField1": {
				"longitude": null,
				"latitude": null
			},
			"loc_locname": "",
			"loc_shopname": "",
			"geoloc_id": 60941,
			"geoloc_uuid": "D6F10309-02F3-B589-BA8F-BB4FCC2F6B6C",
			"targetgroupid": [],
			"store": {
				"stores_id": 830,
				"stores_enterdate": "2015-07-29 15:58:44",
				"stores_title": null,
				"stores_name": "影讯衙门",
				"stores_tel": "",
				"stores_address": null,
				"stores_mark": "",
				"stores_logo_id": 50127,
				"stores_background_id": 0,
				"stores_engname": null,
				"worktime": null,
				"stores_url": "https://www.tsml.com.hk/statichtml/bjmovie01/estores/Home/store.html?stid=830",
				"stores_logo_url": "img.php?sn=202fb910d0950b684b5fb3cdd000c8a3",
				"stores_background_url": "img.php?sn=",
				"favouriteCheck": false
			},
			"likeCount": 0,
			"repostedCount": 0,
			"commentCount": 0,
			"favouriteCheck": false,
			"last_wfforumnote": [],
			"keywords": [
				{
					"keywordtagid": 39,
					"keywordcaption": "影视界"
				},
				{
					"keywordtagid": 109,
					"keywordcaption": "发行"
				}
			],
			"isLiked": false,
			"Ref_feed": [],
			"Ref_user": [],
			"sender_name": "孔利华",
			"sender_pic": "",
			"collections": [
				{
					"collect_id": 74365,
					"col_subject": "",
					"col_body": "",
					"to_ref_url": null,
					"creatoruserid": 3297,
					"enterdate": "2016-04-14 16:02:09",
					"wfemltableid": 134409,
					"wfemltablesn": "J8KX4-TBPWU-G44ZT-SHQO1",
					"elems": [
						{
							"id": 111580,
							"collect_id": 74365,
							"sortorder": 0,
							"creatoruserid": 3297,
							"subject": "",
							"messagebody": "",
							"wfemltableid": 134409,
							"geoloc": null,
							"geoname": "",
							"enterdate": "2016-04-14 16:02:09",
							"deleted": 1,
							"elem_sn": "3XUDX-JP700-09B29-5Q44F",
							"wffilename": "640.jpg",
							"wfextension": "image/jpeg",
							"wfsize": 35203,
							"fileSn": "J8KX4-TBPWU-G44ZT-SHQO1",
							"picwidth": 600,
							"picheight": 338,
							"url": "https://www.tsml.com.hk/statichtml/bjmovie01/site/public/image.php?sn=J8KX4-TBPWU-G44ZT-SHQO1"
						}
					]
				}
			]
		},
		{
			"formdocid": 642683,
			"senderid": 3297,
			"appid": 4,
			"formtypeid": 4,
			"wfstateseq": 6,
			"changedate": "2016-04-14 16:23:40",
			"msubject": "错过“矮大紧”口中最勇敢的电影？看看外国人是怎么评《聚焦》的！ ",
			"message_body": "“矮大紧”这个看起来很猥琐的名字，小影本以为大家都知道是谁，但是经过小范围调查，看来还是很有必要科普一下。矮——大——紧&高——晓——松这是高晓松的一个笔名，配合这个名字的意境，他也经常在这个马甲下发",
			"last_save_date": "2016-04-14 16:23:40",
			"UserVarcharField1": "",
			"UserIntField4": 830,
			"UserIntField5": 50351,
			"UserVarcharField2": "错过“矮大紧”口中最勇敢的电影？看看外国人是怎么评《聚焦》的！ ",
			"UserVarcharField3": "影视圈",
			"UserVarcharField4": "",
			"UserGeoField1": {
				"longitude": null,
				"latitude": null
			},
			"loc_locname": "",
			"loc_shopname": "",
			"geoloc_id": 60940,
			"geoloc_uuid": "77F6B0E9-7F35-2F16-C8DC-6083EE28B849",
			"targetgroupid": [],
			"store": {
				"stores_id": 830,
				"stores_enterdate": "2015-07-29 15:58:44",
				"stores_title": null,
				"stores_name": "影讯衙门",
				"stores_tel": "",
				"stores_address": null,
				"stores_mark": "",
				"stores_logo_id": 50127,
				"stores_background_id": 0,
				"stores_engname": null,
				"worktime": null,
				"stores_url": "https://www.tsml.com.hk/statichtml/bjmovie01/estores/Home/store.html?stid=830",
				"stores_logo_url": "img.php?sn=202fb910d0950b684b5fb3cdd000c8a3",
				"stores_background_url": "img.php?sn=",
				"favouriteCheck": false
			},
			"likeCount": 0,
			"repostedCount": 0,
			"commentCount": 0,
			"favouriteCheck": false,
			"last_wfforumnote": [],
			"keywords": [
				{
					"keywordtagid": 39,
					"keywordcaption": "影视界"
				},
				{
					"keywordtagid": 109,
					"keywordcaption": "发行"
				}
			],
			"isLiked": false,
			"Ref_feed": [],
			"Ref_user": [],
			"sender_name": "孔利华",
			"sender_pic": "",
			"collections": [
				{
					"collect_id": 74364,
					"col_subject": "",
					"col_body": "",
					"to_ref_url": null,
					"creatoruserid": 3297,
					"enterdate": "2016-04-14 16:00:45",
					"wfemltableid": 134408,
					"wfemltablesn": "QIDRD-5Q54K-VBFC2-O6LKF",
					"elems": [
						{
							"id": 111579,
							"collect_id": 74364,
							"sortorder": 0,
							"creatoruserid": 3297,
							"subject": "",
							"messagebody": "",
							"wfemltableid": 134408,
							"geoloc": null,
							"geoname": "",
							"enterdate": "2016-04-14 16:00:45",
							"deleted": 1,
							"elem_sn": "8XVA9-FGDPJ-BJCGW-H8PJK",
							"wffilename": "640.jpg",
							"wfextension": "image/jpeg",
							"wfsize": 17620,
							"fileSn": "QIDRD-5Q54K-VBFC2-O6LKF",
							"picwidth": 640,
							"picheight": 441,
							"url": "https://www.tsml.com.hk/statichtml/bjmovie01/site/public/image.php?sn=QIDRD-5Q54K-VBFC2-O6LKF"
						}
					]
				}
			]
		},
		{
			"formdocid": 642682,
			"senderid": 3297,
			"appid": 4,
			"formtypeid": 4,
			"wfstateseq": 6,
			"changedate": "2016-04-14 16:23:36",
			"msubject": "自媒体野蛮生长 野百合能否有春天 ",
			"message_body": "近日，腾讯宣布启动“芒种计划”，即全面打通企鹅媒体平台，微信、QQ、腾讯新闻、天天快报四大平台，不仅会给予自媒体内容发布的矩阵渠道，还将通过算法增加其流量和收入。对于深耕优质内容的媒体和自媒体，腾讯将",
			"last_save_date": "2016-04-14 16:23:36",
			"UserVarcharField1": "",
			"UserIntField4": 830,
			"UserIntField5": 50346,
			"UserVarcharField2": "2015年下半年，互联网创业遭遇“资本寒冬”。然而在自媒体领域，众多内容创业者却",
			"UserVarcharField3": "综艺",
			"UserVarcharField4": "",
			"UserGeoField1": {
				"longitude": null,
				"latitude": null
			},
			"loc_locname": "",
			"loc_shopname": "",
			"geoloc_id": 60935,
			"geoloc_uuid": "8417BBF8-F2E5-9C0A-B8D6-0B676AE87901",
			"targetgroupid": [],
			"store": {
				"stores_id": 830,
				"stores_enterdate": "2015-07-29 15:58:44",
				"stores_title": null,
				"stores_name": "影讯衙门",
				"stores_tel": "",
				"stores_address": null,
				"stores_mark": "",
				"stores_logo_id": 50127,
				"stores_background_id": 0,
				"stores_engname": null,
				"worktime": null,
				"stores_url": "https://www.tsml.com.hk/statichtml/bjmovie01/estores/Home/store.html?stid=830",
				"stores_logo_url": "img.php?sn=202fb910d0950b684b5fb3cdd000c8a3",
				"stores_background_url": "img.php?sn=",
				"favouriteCheck": false
			},
			"likeCount": 0,
			"repostedCount": 0,
			"commentCount": 0,
			"favouriteCheck": false,
			"last_wfforumnote": [],
			"keywords": [
				{
					"keywordtagid": 39,
					"keywordcaption": "影视界"
				},
				{
					"keywordtagid": 109,
					"keywordcaption": "发行"
				}
			],
			"isLiked": false,
			"Ref_feed": [],
			"Ref_user": [],
			"sender_name": "孔利华",
			"sender_pic": "",
			"collections": [
				{
					"collect_id": 74359,
					"col_subject": "",
					"col_body": "",
					"to_ref_url": null,
					"creatoruserid": 3297,
					"enterdate": "2016-04-14 15:49:58",
					"wfemltableid": 134399,
					"wfemltablesn": "WY8U7-JV8S9-8WNE5-03ISU",
					"elems": [
						{
							"id": 111570,
							"collect_id": 74359,
							"sortorder": 0,
							"creatoruserid": 3297,
							"subject": "",
							"messagebody": "",
							"wfemltableid": 134399,
							"geoloc": null,
							"geoname": "",
							"enterdate": "2016-04-14 15:50:00",
							"deleted": 1,
							"elem_sn": "44UEG-D6QDQ-C7XKB-FKRG8",
							"wffilename": "640.jpg",
							"wfextension": "image/jpeg",
							"wfsize": 19594,
							"fileSn": "WY8U7-JV8S9-8WNE5-03ISU",
							"picwidth": 550,
							"picheight": 289,
							"url": "https://www.tsml.com.hk/statichtml/bjmovie01/site/public/image.php?sn=WY8U7-JV8S9-8WNE5-03ISU"
						}
					]
				}
			]
		},
		{
			"formdocid": 642681,
			"senderid": 3297,
			"appid": 4,
			"formtypeid": 4,
			"wfstateseq": 6,
			"changedate": "2016-04-14 16:23:33",
			"msubject": "不以霸屏为目的的综艺都是耍流氓——捧腹背后 是综艺的血雨腥风 ",
			"message_body": "【导语】经过一季的发酵之后，第二季《欢乐喜剧人》卷土重来之后表现势头更加强劲，在关注度和影响力上几乎横扫一季度综艺，并成功助推东方卫视在一季度登顶收视冠军，这样的成绩着实惊艳到不少行业人士。 一季度已",
			"last_save_date": "2016-04-14 16:23:33",
			"UserVarcharField1": "",
			"UserIntField4": 830,
			"UserIntField5": 50340,
			"UserVarcharField2": "经过一季的发酵之后，第二季《欢乐喜剧人》卷土重来之后表现势头更加强劲，在关注度和",
			"UserVarcharField3": "综艺",
			"UserVarcharField4": "",
			"UserGeoField1": {
				"longitude": null,
				"latitude": null
			},
			"loc_locname": "",
			"loc_shopname": "",
			"geoloc_id": 60929,
			"geoloc_uuid": "28D37C38-84BB-6C2C-2EC1-0A68CA7731E8",
			"targetgroupid": [],
			"store": {
				"stores_id": 830,
				"stores_enterdate": "2015-07-29 15:58:44",
				"stores_title": null,
				"stores_name": "影讯衙门",
				"stores_tel": "",
				"stores_address": null,
				"stores_mark": "",
				"stores_logo_id": 50127,
				"stores_background_id": 0,
				"stores_engname": null,
				"worktime": null,
				"stores_url": "https://www.tsml.com.hk/statichtml/bjmovie01/estores/Home/store.html?stid=830",
				"stores_logo_url": "img.php?sn=202fb910d0950b684b5fb3cdd000c8a3",
				"stores_background_url": "img.php?sn=",
				"favouriteCheck": false
			},
			"likeCount": 0,
			"repostedCount": 0,
			"commentCount": 0,
			"favouriteCheck": false,
			"last_wfforumnote": [],
			"keywords": [
				{
					"keywordtagid": 39,
					"keywordcaption": "影视界"
				},
				{
					"keywordtagid": 109,
					"keywordcaption": "发行"
				}
			],
			"isLiked": false,
			"Ref_feed": [],
			"Ref_user": [],
			"sender_name": "孔利华",
			"sender_pic": "",
			"collections": [
				{
					"collect_id": 74349,
					"col_subject": "",
					"col_body": "",
					"to_ref_url": null,
					"creatoruserid": 3297,
					"enterdate": "2016-04-14 15:34:33",
					"wfemltableid": 134387,
					"wfemltablesn": "K9A1T-LE8GK-5EJN3-BQV8L",
					"elems": [
						{
							"id": 111558,
							"collect_id": 74349,
							"sortorder": 0,
							"creatoruserid": 3297,
							"subject": "",
							"messagebody": "",
							"wfemltableid": 134387,
							"geoloc": null,
							"geoname": "",
							"enterdate": "2016-04-14 15:34:33",
							"deleted": 1,
							"elem_sn": "8IPEV-94WJ6-JKSUE-R644L",
							"wffilename": "640.jpg",
							"wfextension": "image/jpeg",
							"wfsize": 29801,
							"fileSn": "K9A1T-LE8GK-5EJN3-BQV8L",
							"picwidth": 640,
							"picheight": 340,
							"url": "https://www.tsml.com.hk/statichtml/bjmovie01/site/public/image.php?sn=K9A1T-LE8GK-5EJN3-BQV8L"
						}
					]
				}
			]
		},
		{
			"formdocid": 642680,
			"senderid": 3297,
			"appid": 4,
			"formtypeid": 4,
			"wfstateseq": 6,
			"changedate": "2016-04-14 16:23:29",
			"msubject": "全国40家万达影城开启《奇幻森林》VR体验：360度置身热带雨林，巨蟒张口直扑观",
			"message_body": "《奇幻森林》脱胎于迪士尼影业上世纪60年代的经典动画《森林王子》，真人化之后的影片在保留了原有的趣味性同时，也增加了不少精彩刺激的场面。该片将于4月15日上映。影片上映前夕，万达院线与迪士尼独家合作，",
			"last_save_date": "2016-04-14 16:23:29",
			"UserVarcharField1": "",
			"UserIntField4": 830,
			"UserIntField5": 50337,
			"UserVarcharField2": "4月8日，《奇幻森林》上映前期，全国40家万达影城举办了一场特殊的体验活动——V",
			"UserVarcharField3": "第一院线",
			"UserVarcharField4": "",
			"UserGeoField1": {
				"longitude": null,
				"latitude": null
			},
			"loc_locname": "",
			"loc_shopname": "",
			"geoloc_id": 60926,
			"geoloc_uuid": "7C0B9ADC-B94D-1CC3-4C48-CBA4658D9680",
			"targetgroupid": [],
			"store": {
				"stores_id": 830,
				"stores_enterdate": "2015-07-29 15:58:44",
				"stores_title": null,
				"stores_name": "影讯衙门",
				"stores_tel": "",
				"stores_address": null,
				"stores_mark": "",
				"stores_logo_id": 50127,
				"stores_background_id": 0,
				"stores_engname": null,
				"worktime": null,
				"stores_url": "https://www.tsml.com.hk/statichtml/bjmovie01/estores/Home/store.html?stid=830",
				"stores_logo_url": "img.php?sn=202fb910d0950b684b5fb3cdd000c8a3",
				"stores_background_url": "img.php?sn=",
				"favouriteCheck": false
			},
			"likeCount": 0,
			"repostedCount": 0,
			"commentCount": 0,
			"favouriteCheck": false,
			"last_wfforumnote": [],
			"keywords": [
				{
					"keywordtagid": 39,
					"keywordcaption": "影视界"
				},
				{
					"keywordtagid": 109,
					"keywordcaption": "发行"
				}
			],
			"isLiked": false,
			"Ref_feed": [],
			"Ref_user": [],
			"sender_name": "孔利华",
			"sender_pic": "",
			"collections": [
				{
					"collect_id": 74347,
					"col_subject": "",
					"col_body": "",
					"to_ref_url": null,
					"creatoruserid": 3297,
					"enterdate": "2016-04-14 15:32:44",
					"wfemltableid": 134382,
					"wfemltablesn": "SAAUS-QHBRQ-WFHG9-NP5HV",
					"elems": [
						{
							"id": 111553,
							"collect_id": 74347,
							"sortorder": 0,
							"creatoruserid": 3297,
							"subject": "",
							"messagebody": "",
							"wfemltableid": 134382,
							"geoloc": null,
							"geoname": "",
							"enterdate": "2016-04-14 15:32:45",
							"deleted": 1,
							"elem_sn": "4VTI5-6PM8K-DBHGV-EVQDD",
							"wffilename": "640.jpg",
							"wfextension": "image/jpeg",
							"wfsize": 21619,
							"fileSn": "SAAUS-QHBRQ-WFHG9-NP5HV",
							"picwidth": 558,
							"picheight": 368,
							"url": "https://www.tsml.com.hk/statichtml/bjmovie01/site/public/image.php?sn=SAAUS-QHBRQ-WFHG9-NP5HV"
						}
					]
				}
			]
		},
		{
			"formdocid": 642679,
			"senderid": 3297,
			"appid": 4,
			"formtypeid": 4,
			"wfstateseq": 6,
			"changedate": "2016-04-14 16:23:26",
			"msubject": "猫眼电影独立又能怎样：BAT群起而攻之要如何应对 ",
			"message_body": "根据此前的报道，去年12月中旬猫眼电影宣布完成与大众点评电影频道在业务部署、人事安排、产品技术等方面的整合，而在昨日，王兴“内部”宣布合并之后的美团点评正式分拆猫眼电影，成为一家完全独立运营的公司，不",
			"last_save_date": "2016-04-14 16:23:26",
			"UserVarcharField1": "",
			"UserIntField4": 830,
			"UserIntField5": 50336,
			"UserVarcharField2": "根据此前的报道，去年12月中旬猫眼电影宣布完成与大众点评电影频道在业务部署、人事",
			"UserVarcharField3": "第一院线",
			"UserVarcharField4": "",
			"UserGeoField1": {
				"longitude": null,
				"latitude": null
			},
			"loc_locname": "",
			"loc_shopname": "",
			"geoloc_id": 60925,
			"geoloc_uuid": "E4832123-C233-8F73-70E3-B3CBDFBA682E",
			"targetgroupid": [],
			"store": {
				"stores_id": 830,
				"stores_enterdate": "2015-07-29 15:58:44",
				"stores_title": null,
				"stores_name": "影讯衙门",
				"stores_tel": "",
				"stores_address": null,
				"stores_mark": "",
				"stores_logo_id": 50127,
				"stores_background_id": 0,
				"stores_engname": null,
				"worktime": null,
				"stores_url": "https://www.tsml.com.hk/statichtml/bjmovie01/estores/Home/store.html?stid=830",
				"stores_logo_url": "img.php?sn=202fb910d0950b684b5fb3cdd000c8a3",
				"stores_background_url": "img.php?sn=",
				"favouriteCheck": false
			},
			"likeCount": 0,
			"repostedCount": 0,
			"commentCount": 0,
			"favouriteCheck": false,
			"last_wfforumnote": [],
			"keywords": [
				{
					"keywordtagid": 39,
					"keywordcaption": "影视界"
				},
				{
					"keywordtagid": 109,
					"keywordcaption": "发行"
				}
			],
			"isLiked": false,
			"Ref_feed": [],
			"Ref_user": [],
			"sender_name": "孔利华",
			"sender_pic": "",
			"collections": [
				{
					"collect_id": 74346,
					"col_subject": "",
					"col_body": "",
					"to_ref_url": null,
					"creatoruserid": 3297,
					"enterdate": "2016-04-14 15:30:43",
					"wfemltableid": 134381,
					"wfemltablesn": "KGKQ6-6RTI8-KS6IS-37IOX",
					"elems": [
						{
							"id": 111552,
							"collect_id": 74346,
							"sortorder": 0,
							"creatoruserid": 3297,
							"subject": "",
							"messagebody": "",
							"wfemltableid": 134381,
							"geoloc": null,
							"geoname": "",
							"enterdate": "2016-04-14 15:30:43",
							"deleted": 1,
							"elem_sn": "6GT50-52ONF-HBFV1-87ZJN",
							"wffilename": "640.jpg",
							"wfextension": "image/jpeg",
							"wfsize": 36775,
							"fileSn": "KGKQ6-6RTI8-KS6IS-37IOX",
							"picwidth": 640,
							"picheight": 427,
							"url": "https://www.tsml.com.hk/statichtml/bjmovie01/site/public/image.php?sn=KGKQ6-6RTI8-KS6IS-37IOX"
						}
					]
				}
			]
		},
		{
			"formdocid": 642678,
			"senderid": 3297,
			"appid": 4,
			"formtypeid": 4,
			"wfstateseq": 6,
			"changedate": "2016-04-14 16:23:14",
			"msubject": "被今年的大片阵容吓尿了！22部你起码会看一半",
			"message_body": "千万不要因为《超人大干蝙蝠侠》没干爽，就对2016年绝望。今年是名副其实的「超级大片年」——从动画到真人，从漫威到DC，从森林到仙境……值得期待的大牌巨制实在太多了！院长今天挑选了最可能引爆口碑和票房",
			"last_save_date": "2016-04-14 16:23:14",
			"UserVarcharField1": "",
			"UserIntField4": 830,
			"UserIntField5": 50332,
			"UserVarcharField2": "千万不要因为《超人大干蝙蝠侠》没干爽，就对2016年绝望。",
			"UserVarcharField3": "第一院线",
			"UserVarcharField4": "",
			"UserGeoField1": {
				"longitude": null,
				"latitude": null
			},
			"loc_locname": "",
			"loc_shopname": "",
			"geoloc_id": 60917,
			"geoloc_uuid": "9002112C-D871-BDF1-D42C-8E667DB796BA",
			"targetgroupid": [],
			"store": {
				"stores_id": 830,
				"stores_enterdate": "2015-07-29 15:58:44",
				"stores_title": null,
				"stores_name": "影讯衙门",
				"stores_tel": "",
				"stores_address": null,
				"stores_mark": "",
				"stores_logo_id": 50127,
				"stores_background_id": 0,
				"stores_engname": null,
				"worktime": null,
				"stores_url": "https://www.tsml.com.hk/statichtml/bjmovie01/estores/Home/store.html?stid=830",
				"stores_logo_url": "img.php?sn=202fb910d0950b684b5fb3cdd000c8a3",
				"stores_background_url": "img.php?sn=",
				"favouriteCheck": false
			},
			"likeCount": 0,
			"repostedCount": 0,
			"commentCount": 0,
			"favouriteCheck": false,
			"last_wfforumnote": [],
			"keywords": [
				{
					"keywordtagid": 39,
					"keywordcaption": "影视界"
				},
				{
					"keywordtagid": 109,
					"keywordcaption": "发行"
				}
			],
			"isLiked": false,
			"Ref_feed": [],
			"Ref_user": [],
			"sender_name": "孔利华",
			"sender_pic": "",
			"collections": [
				{
					"collect_id": 74343,
					"col_subject": "",
					"col_body": "",
					"to_ref_url": null,
					"creatoruserid": 3297,
					"enterdate": "2016-04-14 15:25:18",
					"wfemltableid": 134378,
					"wfemltablesn": "YBY65-8DVMB-UJ3AZ-NC5CR",
					"elems": [
						{
							"id": 111549,
							"collect_id": 74343,
							"sortorder": 0,
							"creatoruserid": 3297,
							"subject": "",
							"messagebody": "",
							"wfemltableid": 134378,
							"geoloc": null,
							"geoname": "",
							"enterdate": "2016-04-14 15:25:19",
							"deleted": 1,
							"elem_sn": "2X58U-7RYIQ-5VU0T-84FWK",
							"wffilename": "640.jpg",
							"wfextension": "image/jpeg",
							"wfsize": 52111,
							"fileSn": "YBY65-8DVMB-UJ3AZ-NC5CR",
							"picwidth": 600,
							"picheight": 296,
							"url": "https://www.tsml.com.hk/statichtml/bjmovie01/site/public/image.php?sn=YBY65-8DVMB-UJ3AZ-NC5CR"
						}
					]
				}
			]
		},
		{
			"formdocid": 642677,
			"senderid": 3297,
			"appid": 4,
			"formtypeid": 4,
			"wfstateseq": 6,
			"changedate": "2016-04-14 16:23:10",
			"msubject": "全国影院竞争分析报告：该到哪去开影院，啥样的影院经营好 ",
			"message_body": "一线城市竞争分析 一线城市（北京、上海、深圳、广州）无论是在票房、观影人次还是影院、银幕的总量上都继续保持了极大的领先优势，但是在增速上都普遍放缓，在基数已经极大化的前提下，增速放缓也是基本的发展规律",
			"last_save_date": "2016-04-14 16:23:10",
			"UserVarcharField1": "",
			"UserIntField4": 830,
			"UserIntField5": 50328,
			"UserVarcharField2": "一线城市（北京、上海、深圳、广州）无论是在票房、观影人次还是影院、银幕的总量上都",
			"UserVarcharField3": "第一院线",
			"UserVarcharField4": "",
			"UserGeoField1": {
				"longitude": null,
				"latitude": null
			},
			"loc_locname": "",
			"loc_shopname": "",
			"geoloc_id": 60913,
			"geoloc_uuid": "CFF42E02-FC8A-8530-150E-BB4AD1CF9F97",
			"targetgroupid": [],
			"store": {
				"stores_id": 830,
				"stores_enterdate": "2015-07-29 15:58:44",
				"stores_title": null,
				"stores_name": "影讯衙门",
				"stores_tel": "",
				"stores_address": null,
				"stores_mark": "",
				"stores_logo_id": 50127,
				"stores_background_id": 0,
				"stores_engname": null,
				"worktime": null,
				"stores_url": "https://www.tsml.com.hk/statichtml/bjmovie01/estores/Home/store.html?stid=830",
				"stores_logo_url": "img.php?sn=202fb910d0950b684b5fb3cdd000c8a3",
				"stores_background_url": "img.php?sn=",
				"favouriteCheck": false
			},
			"likeCount": 0,
			"repostedCount": 0,
			"commentCount": 0,
			"favouriteCheck": false,
			"last_wfforumnote": [],
			"keywords": [
				{
					"keywordtagid": 39,
					"keywordcaption": "影视界"
				}
			],
			"isLiked": false,
			"Ref_feed": [],
			"Ref_user": [],
			"sender_name": "孔利华",
			"sender_pic": "",
			"collections": [
				{
					"collect_id": 74340,
					"col_subject": "",
					"col_body": "",
					"to_ref_url": null,
					"creatoruserid": 3297,
					"enterdate": "2016-04-14 15:17:16",
					"wfemltableid": 134375,
					"wfemltablesn": "F368P-FRD5X-M97J6-FN9UV",
					"elems": [
						{
							"id": 111546,
							"collect_id": 74340,
							"sortorder": 0,
							"creatoruserid": 3297,
							"subject": "",
							"messagebody": "",
							"wfemltableid": 134375,
							"geoloc": null,
							"geoname": "",
							"enterdate": "2016-04-14 15:17:17",
							"deleted": 1,
							"elem_sn": "2C5TI-59XMK-ML4LU-OQTYD",
							"wffilename": "640.jpg",
							"wfextension": "image/jpeg",
							"wfsize": 17664,
							"fileSn": "F368P-FRD5X-M97J6-FN9UV",
							"picwidth": 448,
							"picheight": 299,
							"url": "https://www.tsml.com.hk/statichtml/bjmovie01/site/public/image.php?sn=F368P-FRD5X-M97J6-FN9UV"
						}
					]
				}
			]
		},
		{
			"formdocid": 620794,
			"senderid": 3297,
			"appid": 4,
			"formtypeid": 4,
			"wfstateseq": 6,
			"changedate": "2016-04-13 16:51:01",
			"msubject": "导演和摄影必须知道的12件事 ",
			"message_body": "不论你是在有着大把钞票的大电影剧组，还是穷的可怜的独立电影，有一件事是肯定的，想要把电影拍好，就是剧组上上下下每个人都必须尽100%的努力。但往往追求完美的心态，在高强度工作的压力下，会在人与人之间制",
			"last_save_date": "2016-04-13 16:51:01",
			"UserVarcharField1": "",
			"UserIntField4": 830,
			"UserIntField5": 49979,
			"UserVarcharField2": "不论你是在有着大把钞票的大电影剧组，还是穷的可怜的独立电影，有一件事是肯定的，想",
			"UserVarcharField3": "影视新生代",
			"UserVarcharField4": "",
			"UserGeoField1": {
				"longitude": null,
				"latitude": null
			},
			"loc_locname": "",
			"loc_shopname": "",
			"geoloc_id": 60290,
			"geoloc_uuid": "005F505A-F7F4-E364-3AAA-2E4BD2B9D19A",
			"targetgroupid": [],
			"store": {
				"stores_id": 830,
				"stores_enterdate": "2015-07-29 15:58:44",
				"stores_title": null,
				"stores_name": "影讯衙门",
				"stores_tel": "",
				"stores_address": null,
				"stores_mark": "",
				"stores_logo_id": 50127,
				"stores_background_id": 0,
				"stores_engname": null,
				"worktime": null,
				"stores_url": "https://www.tsml.com.hk/statichtml/bjmovie01/estores/Home/store.html?stid=830",
				"stores_logo_url": "img.php?sn=202fb910d0950b684b5fb3cdd000c8a3",
				"stores_background_url": "img.php?sn=",
				"favouriteCheck": false
			},
			"likeCount": 0,
			"repostedCount": 0,
			"commentCount": 0,
			"favouriteCheck": false,
			"last_wfforumnote": [],
			"keywords": [
				{
					"keywordtagid": 39,
					"keywordcaption": "影视界"
				},
				{
					"keywordtagid": 125,
					"keywordcaption": "设备"
				}
			],
			"isLiked": false,
			"Ref_feed": [],
			"Ref_user": [],
			"sender_name": "孔利华",
			"sender_pic": "",
			"collections": [
				{
					"collect_id": 73950,
					"col_subject": "",
					"col_body": "",
					"to_ref_url": null,
					"creatoruserid": 3297,
					"enterdate": "2016-04-13 15:22:17",
					"wfemltableid": 133735,
					"wfemltablesn": "3GJAR-A19PA-JNS4W-JJEID",
					"elems": [
						{
							"id": 110967,
							"collect_id": 73950,
							"sortorder": 0,
							"creatoruserid": 3297,
							"subject": "",
							"messagebody": "",
							"wfemltableid": 133735,
							"geoloc": null,
							"geoname": "",
							"enterdate": "2016-04-13 15:22:19",
							"deleted": 1,
							"elem_sn": "7S05N-EHWLN-PZ7P1-3L5CT",
							"wffilename": "640.jpg",
							"wfextension": "image/jpeg",
							"wfsize": 48122,
							"fileSn": "3GJAR-A19PA-JNS4W-JJEID",
							"picwidth": 638,
							"picheight": 707,
							"url": "https://www.tsml.com.hk/statichtml/bjmovie01/site/public/image.php?sn=3GJAR-A19PA-JNS4W-JJEID"
						}
					]
				}
			]
		},
		{
			"formdocid": 620791,
			"senderid": 3297,
			"appid": 4,
			"formtypeid": 4,
			"wfstateseq": 6,
			"changedate": "2016-04-13 16:50:56",
			"msubject": "北京这些名字超有趣儿的胡同，你都去过了吗?",
			"message_body": "之所以把百花深处放在第一位来说，纯属是我个人偏好，觉得这是最美的胡同名，没有之一。以前总听《北京一夜》，其中的一段歌词是这样写的“人说百花的深处，住着老情人缝着绣花鞋，面容安详的老人，依旧等着那出征的",
			"last_save_date": "2016-04-13 16:50:56",
			"UserVarcharField1": "",
			"UserIntField4": 830,
			"UserIntField5": 49982,
			"UserVarcharField2": "之所以把百花深处放在第一位来说，纯属是我个人偏好，觉得这是最美的胡同名，没有之一",
			"UserVarcharField3": "和沐传媒",
			"UserVarcharField4": "",
			"UserGeoField1": {
				"longitude": null,
				"latitude": null
			},
			"loc_locname": "",
			"loc_shopname": "",
			"geoloc_id": 60293,
			"geoloc_uuid": "925C85C7-B8D4-98BC-17F9-8CE64184B895",
			"targetgroupid": [],
			"store": {
				"stores_id": 830,
				"stores_enterdate": "2015-07-29 15:58:44",
				"stores_title": null,
				"stores_name": "影讯衙门",
				"stores_tel": "",
				"stores_address": null,
				"stores_mark": "",
				"stores_logo_id": 50127,
				"stores_background_id": 0,
				"stores_engname": null,
				"worktime": null,
				"stores_url": "https://www.tsml.com.hk/statichtml/bjmovie01/estores/Home/store.html?stid=830",
				"stores_logo_url": "img.php?sn=202fb910d0950b684b5fb3cdd000c8a3",
				"stores_background_url": "img.php?sn=",
				"favouriteCheck": false
			},
			"likeCount": 0,
			"repostedCount": 0,
			"commentCount": 0,
			"favouriteCheck": false,
			"last_wfforumnote": [],
			"keywords": [
				{
					"keywordtagid": 39,
					"keywordcaption": "影视界"
				},
				{
					"keywordtagid": 118,
					"keywordcaption": "场地"
				}
			],
			"isLiked": false,
			"Ref_feed": [],
			"Ref_user": [],
			"sender_name": "孔利华",
			"sender_pic": "",
			"collections": [
				{
					"collect_id": 73952,
					"col_subject": "",
					"col_body": "",
					"to_ref_url": null,
					"creatoruserid": 3297,
					"enterdate": "2016-04-13 15:24:12",
					"wfemltableid": 133738,
					"wfemltablesn": "FUZXJ-WNH5T-RAAGG-PQEYE",
					"elems": [
						{
							"id": 110970,
							"collect_id": 73952,
							"sortorder": 0,
							"creatoruserid": 3297,
							"subject": "",
							"messagebody": "",
							"wfemltableid": 133738,
							"geoloc": null,
							"geoname": "",
							"enterdate": "2016-04-13 15:24:14",
							"deleted": 1,
							"elem_sn": "96T7B-LCEO9-6MVDC-XAXI3",
							"wffilename": "640.jpg",
							"wfextension": "image/jpeg",
							"wfsize": 19565,
							"fileSn": "FUZXJ-WNH5T-RAAGG-PQEYE",
							"picwidth": 357,
							"picheight": 246,
							"url": "https://www.tsml.com.hk/statichtml/bjmovie01/site/public/image.php?sn=FUZXJ-WNH5T-RAAGG-PQEYE"
						}
					]
				}
			]
		},
		{
			"formdocid": 620790,
			"senderid": 3297,
			"appid": 4,
			"formtypeid": 4,
			"wfstateseq": 6,
			"changedate": "2016-04-13 16:50:40",
			"msubject": "2016是电视台的“剧荒”之年吗？ ",
			"message_body": "原本以为，一剧两星可以刺激电视剧的生产与供给，缓解电视台扎堆拼播大剧的现状，也可以让观众有更多的观剧选择。不过，从一年多来的政策施行情况看，结果并不如预期。2015年，电视剧收视市场整体萎缩，收视率破",
			"last_save_date": "2016-04-13 16:50:40",
			"UserVarcharField1": "",
			"UserIntField4": 830,
			"UserIntField5": 49994,
			"UserVarcharField2": "原本以为，一剧两星可以刺激电视剧的生产与供给，缓解电视台扎堆拼播大剧的现状，也可",
			"UserVarcharField3": "媒介360",
			"UserVarcharField4": "",
			"UserGeoField1": {
				"longitude": null,
				"latitude": null
			},
			"loc_locname": "",
			"loc_shopname": "",
			"geoloc_id": 60305,
			"geoloc_uuid": "03C12D2D-E958-381C-B3DA-0245E7DB4ADE",
			"targetgroupid": [],
			"store": {
				"stores_id": 830,
				"stores_enterdate": "2015-07-29 15:58:44",
				"stores_title": null,
				"stores_name": "影讯衙门",
				"stores_tel": "",
				"stores_address": null,
				"stores_mark": "",
				"stores_logo_id": 50127,
				"stores_background_id": 0,
				"stores_engname": null,
				"worktime": null,
				"stores_url": "https://www.tsml.com.hk/statichtml/bjmovie01/estores/Home/store.html?stid=830",
				"stores_logo_url": "img.php?sn=202fb910d0950b684b5fb3cdd000c8a3",
				"stores_background_url": "img.php?sn=",
				"favouriteCheck": false
			},
			"likeCount": 0,
			"repostedCount": 0,
			"commentCount": 0,
			"favouriteCheck": false,
			"last_wfforumnote": [],
			"keywords": [
				{
					"keywordtagid": 39,
					"keywordcaption": "影视界"
				},
				{
					"keywordtagid": 109,
					"keywordcaption": "发行"
				}
			],
			"isLiked": false,
			"Ref_feed": [],
			"Ref_user": [],
			"sender_name": "孔利华",
			"sender_pic": "",
			"collections": [
				{
					"collect_id": 73975,
					"col_subject": "",
					"col_body": "",
					"to_ref_url": null,
					"creatoruserid": 3297,
					"enterdate": "2016-04-13 15:52:30",
					"wfemltableid": 133778,
					"wfemltablesn": "S8O37-W3U7D-0FFPL-4QZVV",
					"elems": [
						{
							"id": 111010,
							"collect_id": 73975,
							"sortorder": 0,
							"creatoruserid": 3297,
							"subject": "",
							"messagebody": "",
							"wfemltableid": 133778,
							"geoloc": null,
							"geoname": "",
							"enterdate": "2016-04-13 15:52:31",
							"deleted": 1,
							"elem_sn": "51P6I-X9MGD-9491M-3ZU68",
							"wffilename": "640.jpg",
							"wfextension": "image/jpeg",
							"wfsize": 63755,
							"fileSn": "S8O37-W3U7D-0FFPL-4QZVV",
							"picwidth": 640,
							"picheight": 410,
							"url": "https://www.tsml.com.hk/statichtml/bjmovie01/site/public/image.php?sn=S8O37-W3U7D-0FFPL-4QZVV"
						}
					]
				}
			]
		},
		{
			"formdocid": 620789,
			"senderid": 3297,
			"appid": 4,
			"formtypeid": 4,
			"wfstateseq": 6,
			"changedate": "2016-04-13 16:50:32",
			"msubject": "变革时代，老公司如何不被新公司打败？",
			"message_body": "在一个大变革的时代，过去的经验大多不再适用，而真正敢说能预知未来的人，几乎是没有的。这就导致了当今企业普遍存在战略的窘境。 突破眼光局限用组织的方式，解决战略的问题 假如说我们在变革时代看到未来有10",
			"last_save_date": "2016-04-13 16:50:32",
			"UserVarcharField1": "",
			"UserIntField4": 830,
			"UserIntField5": 50011,
			"UserVarcharField2": "在一个大变革的时代，过去的经验大多不再适用，而真正敢说能预知未来的人，几乎是没有",
			"UserVarcharField3": "媒介360",
			"UserVarcharField4": "",
			"UserGeoField1": {
				"longitude": null,
				"latitude": null
			},
			"loc_locname": "",
			"loc_shopname": "",
			"geoloc_id": 60322,
			"geoloc_uuid": "746230B7-2B3E-1BBA-CD52-213BA9BF8876",
			"targetgroupid": [],
			"store": {
				"stores_id": 830,
				"stores_enterdate": "2015-07-29 15:58:44",
				"stores_title": null,
				"stores_name": "影讯衙门",
				"stores_tel": "",
				"stores_address": null,
				"stores_mark": "",
				"stores_logo_id": 50127,
				"stores_background_id": 0,
				"stores_engname": null,
				"worktime": null,
				"stores_url": "https://www.tsml.com.hk/statichtml/bjmovie01/estores/Home/store.html?stid=830",
				"stores_logo_url": "img.php?sn=202fb910d0950b684b5fb3cdd000c8a3",
				"stores_background_url": "img.php?sn=",
				"favouriteCheck": false
			},
			"likeCount": 0,
			"repostedCount": 0,
			"commentCount": 0,
			"favouriteCheck": false,
			"last_wfforumnote": [],
			"keywords": [
				{
					"keywordtagid": 39,
					"keywordcaption": "影视界"
				},
				{
					"keywordtagid": 109,
					"keywordcaption": "发行"
				}
			],
			"isLiked": false,
			"Ref_feed": [],
			"Ref_user": [],
			"sender_name": "孔利华",
			"sender_pic": "",
			"collections": [
				{
					"collect_id": 73981,
					"col_subject": "",
					"col_body": "",
					"to_ref_url": null,
					"creatoruserid": 3297,
					"enterdate": "2016-04-13 15:57:55",
					"wfemltableid": 133787,
					"wfemltablesn": "3PUVQ-R0AZ7-X9ZDN-O9D04",
					"elems": [
						{
							"id": 111019,
							"collect_id": 73981,
							"sortorder": 0,
							"creatoruserid": 3297,
							"subject": "",
							"messagebody": "",
							"wfemltableid": 133787,
							"geoloc": null,
							"geoname": "",
							"enterdate": "2016-04-13 15:57:57",
							"deleted": 1,
							"elem_sn": "77CXD-SX71E-WXXHR-AG9N0",
							"wffilename": "640.jpg",
							"wfextension": "image/jpeg",
							"wfsize": 22154,
							"fileSn": "3PUVQ-R0AZ7-X9ZDN-O9D04",
							"picwidth": 640,
							"picheight": 296,
							"url": "https://www.tsml.com.hk/statichtml/bjmovie01/site/public/image.php?sn=3PUVQ-R0AZ7-X9ZDN-O9D04"
						}
					]
				}
			]
		},
		{
			"formdocid": 620788,
			"senderid": 3297,
			"appid": 4,
			"formtypeid": 4,
			"wfstateseq": 6,
			"changedate": "2016-04-13 16:50:26",
			"msubject": "从《敢死队》到《伦敦陷落》，好莱坞传统动作大片还有机会么",
			"message_body": "《伦敦陷落》在内地的成绩又超过了北美《伦敦陷落》上个周末在内地大卖了1.58亿，以明显的优势超越了一个月前北美首周末的2164万美金。从2013年暑期档《环太平洋》标志性地内地票房首超北美之后，好莱坞",
			"last_save_date": "2016-04-13 16:50:26",
			"UserVarcharField1": "",
			"UserIntField4": 830,
			"UserIntField5": 50016,
			"UserVarcharField2": "《伦敦陷落》上个周末在内地大卖了1.58亿，以明显的优势超越了一个月前北美首周末",
			"UserVarcharField3": "第一院线",
			"UserVarcharField4": "",
			"UserGeoField1": {
				"longitude": null,
				"latitude": null
			},
			"loc_locname": "",
			"loc_shopname": "",
			"geoloc_id": 60327,
			"geoloc_uuid": "F4D9BC91-948B-39F6-5214-6F9D887A1466",
			"targetgroupid": [],
			"store": {
				"stores_id": 830,
				"stores_enterdate": "2015-07-29 15:58:44",
				"stores_title": null,
				"stores_name": "影讯衙门",
				"stores_tel": "",
				"stores_address": null,
				"stores_mark": "",
				"stores_logo_id": 50127,
				"stores_background_id": 0,
				"stores_engname": null,
				"worktime": null,
				"stores_url": "https://www.tsml.com.hk/statichtml/bjmovie01/estores/Home/store.html?stid=830",
				"stores_logo_url": "img.php?sn=202fb910d0950b684b5fb3cdd000c8a3",
				"stores_background_url": "img.php?sn=",
				"favouriteCheck": false
			},
			"likeCount": 0,
			"repostedCount": 0,
			"commentCount": 0,
			"favouriteCheck": false,
			"last_wfforumnote": [],
			"keywords": [
				{
					"keywordtagid": 39,
					"keywordcaption": "影视界"
				},
				{
					"keywordtagid": 109,
					"keywordcaption": "发行"
				}
			],
			"isLiked": false,
			"Ref_feed": [],
			"Ref_user": [],
			"sender_name": "孔利华",
			"sender_pic": "",
			"collections": [
				{
					"collect_id": 73985,
					"col_subject": "",
					"col_body": "",
					"to_ref_url": null,
					"creatoruserid": 3297,
					"enterdate": "2016-04-13 16:02:07",
					"wfemltableid": 133791,
					"wfemltablesn": "6JPSC-XPGCH-I3VKI-4PO9Y",
					"elems": [
						{
							"id": 111023,
							"collect_id": 73985,
							"sortorder": 0,
							"creatoruserid": 3297,
							"subject": "",
							"messagebody": "",
							"wfemltableid": 133791,
							"geoloc": null,
							"geoname": "",
							"enterdate": "2016-04-13 16:02:09",
							"deleted": 1,
							"elem_sn": "02GLO-T56S6-FIHL4-G0FLE",
							"wffilename": "640.jpg",
							"wfextension": "image/jpeg",
							"wfsize": 24353,
							"fileSn": "6JPSC-XPGCH-I3VKI-4PO9Y",
							"picwidth": 600,
							"picheight": 399,
							"url": "https://www.tsml.com.hk/statichtml/bjmovie01/site/public/image.php?sn=6JPSC-XPGCH-I3VKI-4PO9Y"
						}
					]
				}
			]
		},
		{
			"formdocid": 620787,
			"senderid": 3297,
			"appid": 4,
			"formtypeid": 4,
			"wfstateseq": 6,
			"changedate": "2016-04-13 16:50:21",
			"msubject": "栗坤与马东“定制互动”，《幸福的味道》如此创新太抢眼！",
			"message_body": "昨晚，《幸福的味道》登陆北京卫视，马东携《奇葩说》的辩手范湉湉、颜如晶、樊野、陈铭齐齐亮相。节目播出后反响热烈，在微博话题榜、搜索榜、综艺榜上遥遥领先。关注度如此之高，并不只是因为有栗坤、马东和多位网",
			"last_save_date": "2016-04-13 16:50:21",
			"UserVarcharField1": "",
			"UserIntField4": 830,
			"UserIntField5": 50020,
			"UserVarcharField2": "昨晚，《幸福的味道》登陆北京卫视，马东携《奇葩说》的辩手范湉湉、颜如晶、樊野、陈",
			"UserVarcharField3": "广电独家",
			"UserVarcharField4": "",
			"UserGeoField1": {
				"longitude": null,
				"latitude": null
			},
			"loc_locname": "",
			"loc_shopname": "",
			"geoloc_id": 60331,
			"geoloc_uuid": "8E1FBA7E-FC70-FC46-C41C-C516878AC9E1",
			"targetgroupid": [],
			"store": {
				"stores_id": 830,
				"stores_enterdate": "2015-07-29 15:58:44",
				"stores_title": null,
				"stores_name": "影讯衙门",
				"stores_tel": "",
				"stores_address": null,
				"stores_mark": "",
				"stores_logo_id": 50127,
				"stores_background_id": 0,
				"stores_engname": null,
				"worktime": null,
				"stores_url": "https://www.tsml.com.hk/statichtml/bjmovie01/estores/Home/store.html?stid=830",
				"stores_logo_url": "img.php?sn=202fb910d0950b684b5fb3cdd000c8a3",
				"stores_background_url": "img.php?sn=",
				"favouriteCheck": false
			},
			"likeCount": 0,
			"repostedCount": 0,
			"commentCount": 0,
			"favouriteCheck": false,
			"last_wfforumnote": [],
			"keywords": [
				{
					"keywordtagid": 39,
					"keywordcaption": "影视界"
				},
				{
					"keywordtagid": 109,
					"keywordcaption": "发行"
				}
			],
			"isLiked": false,
			"Ref_feed": [],
			"Ref_user": [],
			"sender_name": "孔利华",
			"sender_pic": "",
			"collections": [
				{
					"collect_id": 73994,
					"col_subject": "",
					"col_body": "",
					"to_ref_url": null,
					"creatoruserid": 3297,
					"enterdate": "2016-04-13 16:09:51",
					"wfemltableid": 133807,
					"wfemltablesn": "MOU0W-0CQD2-AGE40-5JDWN",
					"elems": [
						{
							"id": 111039,
							"collect_id": 73994,
							"sortorder": 0,
							"creatoruserid": 3297,
							"subject": "",
							"messagebody": "",
							"wfemltableid": 133807,
							"geoloc": null,
							"geoname": "",
							"enterdate": "2016-04-13 16:09:52",
							"deleted": 1,
							"elem_sn": "9C9K5-ZG07Y-HU4ED-59W4P",
							"wffilename": "640.jpg",
							"wfextension": "image/jpeg",
							"wfsize": 34445,
							"fileSn": "MOU0W-0CQD2-AGE40-5JDWN",
							"picwidth": 640,
							"picheight": 468,
							"url": "https://www.tsml.com.hk/statichtml/bjmovie01/site/public/image.php?sn=MOU0W-0CQD2-AGE40-5JDWN"
						}
					]
				}
			]
		}
	],
	"message": ""
}